Workbook
Name Perpetual_Growth_Rate: Model!$E$140
Name Riskfreerate: WACC!$H$45
Name WACC: Model!$E$141

Sheet Index 
A1: Star Cements
A2: Index Sheet
C4: Sheet Name | D4: Description | E4: Purpose
C5: Assumptions | D5: Key assumptions, company data, valuation output | E5: Starting point
C6: Historical | D6: 5-year audited financials (FY2022–FY2026) | E6: Base data
C7: Model | D7: Integrated 3-statement forecast (FY2027–FY2036) | E7: Core model
C8: Ratio Analysis | D8: Historical + forecast ratio dashboard | E8: Performance metrics
C9: Scenario Analysis | D9: Base / Bull / Bear DCF scenarios | E9: Sensitivity
C10: Comps | D10: Peer trading comparables | E10: Relative valuation
C11: Comp Data | D11: Raw peer financial data | E11: Source for Comps
C12: WACC | D12: WACC build (cost of equity, cost of debt) | E12: Discount rate
C13: Beta | D13: Regression beta calculation | E13: Beta derivation
C14: Market Data | D14: CMP, market cap, peer prices | E14: Market reference
C15: Football Field Analysis | D15: Valuation range across methodologies | E15: Summary visual

Sheet Assumptions
A1: Star Cements
A2: Assumptions Sheet
B4: Company Description | C4: =A1 -> Star Cements | D4: About Firm
B5: ISIN Code | C5: INE460H01021 | D5: Star Cement Limited (formerly Cement Manufacturing Company Limited, renamed in 2016) is the largest cement manufacturer in North East India, with its integrated plant at Lumshnong, Meghalaya and grinding units serving the North-East, West Bengal and Bihar. Promoted by the Bhajanka family (Century Plyboards group) and founded in 2001, the company manufactures OPC, PPC, PSC and value-added cement variants. It is listed on both the NSE and BSE.
B6: Sector Name | C6: Materials
B7: Industry | C7: Cement & Cement Products
B8: Exchange Name | C8: BSE: 540575, NSE: STARCEMENT
B9: Website | C9: www.starcement.co.in
B10: Current Market Price | C10: =H17 -> 198.94
B13: Section | C13: Assumption | F13: Company Data
B14: Revenue | F14: Particulars | H14: Amounts
B15: Revenue — Base Case | C15: Base Case revenue growth of 13.00% in FY2027, tapered annually at 10% to 5% by FY2036. | F15: No. of Outstanding Shares | G15: Nos | H15: ='Comp Data'!I14*10000000 -> 404200000
B16: Revenue — Bull Case | C16: Bull Case opening growth of 22.25% (FY2023 peak historical growth), tapered at 10% per year using identical tapering logic. | F16: Face Value per Share | G16: Rs. | H16: 1
B17: Revenue — Bear Case | C17: Bear Case revenue growth of 7.5% in FY2027, broadly aligned with the 7–8% industry growth outlook, tapered annually to 4% by FY2036 | F17: Current Market Price | G17: Rs. | H17: =Comps!H19 -> 198.94
B18: Base Year Revenue | C18: FY2026 audited revenue of ₹3,795.75 Cr serves as the base for all growth projections. | F18: Market Capitalisation | G18: ₹ in Cr | H18: =H17*H15/10000000 -> 8041.1548
B19: COSTS & EXPENSES
B20: COGS | C20: COGS modelled at 15.56% of revenue; FY2024–FY2026 (3-year) historical average, held flat through the forecast.
B21: Salaries & Benefits | C21: Salaries & Benefits fixed at 7.32% of revenue; FY2022–FY2026 (5-year) historical average. | F21: Key Metrics
B22: Other SG&A | C22: Other SG&A fixed at 54.00% of revenue; FY2022–FY2026 (5-year) historical average.
B23: Other Income | C23: Other income is embedded within Total Income (Revenue) and not forecast as a separate line; FY2022–FY2026 average was ~0.6% of core sales. | F23: Particulars | G23: Unit | H23: Amount
B24: Exceptional Items | C24: Exceptional items set to zero across all forecast years (FY2026 actual exceptional gain of ₹11.32 Cr treated as non-recurring). | F24: Revenue Growth — Base Case | G24: % | H24: {='Scenario Analysis'!E5:E8} -> 0.13
B25: DEPRECIATION & CAPEX | F25: Revenue Growth — Bull Case | G25: % | H25: 0.22248176
B26: Depreciation Rate | C26: D&A at 15.22% of opening PP&E (FY2026 rate); stepped up +2.00% every three years from FY2030. | F26: Revenue Growth — Bear Case | G26: % | H26: 0.075
B27: Capital Expenditure | C27: Capex modelled as % of revenue: 13.75% (FY2027), 28.23% (FY2028), 21.53% (FY2029) reflecting the capacity-expansion plan, then tapering -3.00% p.a. thereafter to 2.93% by FY2036 (₹600 Cr FY2027 capex). | F27: Annual Tapering in Growth Rate | G27: % | H27: 0.1
B28: TAXATION | F28: EBITDA Margin (FY2026 Actual) | G28: % | H28: =Model!L29/Model!L23 -> 0.25165321
B29: Base Tax Rate | C29: Effective tax rate starts at 25.56% (FY2026 actual rate). | F29: PAT Margin (FY2026 Actual) | G29: % | H29: =Model!L37/Model!L23 -> 0.10883106
B30: Tax Rate Step-Up | C30: Tax rate stepped up +0.50% every two years, reaching 28.06% by FY2036. | F30: Effective Tax Rate | G30: % | H30: =Model!M13 -> 0.25560461
B31: WORKING CAPITAL | F31: Perpetual Growth Rate | G31: % | H31: =Model!E140 -> 0.04
B32: Receivables (DSO) | C32: DSO of 18.17 days; FY2023–FY2026 (4-year) historical average on a 365-day convention. | F32: Risk-Free Rate (10yr G-Sec) | G32: % | H32: =WACC!H45 -> 0.0703
B33: Inventory (DIO) | C33: DIO of 257.09 days; FY2023–FY2026 (4-year) historical average — reflects large limestone/coal/clinker stockpiles typical of an integrated cement manufacturer. | F33: Equity Risk Premium | G33: % | H33: =WACC!H47 -> 0.045316819
B34: Payables (DPO) | C34: DPO of 165.81 days; FY2023–FY2026 (4-year) historical average on a 365-day convention. | F34: Equity Beta (Regression) | G34: x | H34: =Beta!I11 -> 0.72968523
B35: Cash Conversion Cycle | C35: Net CCC of +109.45 days, driven by heavy raw-material inventory holding typical of cement manufacturing; modelled as persistent. | F35: Levered Equity Beta (Used) | G35: x | H35: =WACC!H48 -> 1.0221167
B36: Non-Cash WC Movements | C36: Non-cash working capital items (Other Current Assets/Liabilities) held flat at FY2026 levels; historically volatile and not reliably forecastable. | F36: Cost of Equity | G36: % | H36: =WACC!H49 -> 0.11661908
B37: BALANCE SHEET | F37: Pre-Tax Cost of Debt | G37: % | H37: =WACC!H40 -> 0.057931467
B38: Cash & Equivalents | C38: Cash is the balancing figure in the Balance Sheet; accumulates from ₹571.21 Cr (FY2027) to ₹6,708.51 Cr (FY2036). | F38: After-Tax Cost of Debt | G38: % | H38: =WACC!H42 -> 0.043123917
B39: Frozen BS Items | C39: All non-operating balance sheet items held flat at FY2026 audited balances throughout the forecast. | F39: WACC | G39: % | H39: =WACC!H51 -> 0.10730595
B40: CAPITAL STRUCTURE | F40: Intrinsic Value (DCF) | G40: ₹/share | H40: =Model!E173 -> 275.98695
B41: Total Debt | C41: Debt frozen at ₹493.19 Cr throughout forecast; no new borrowings or repayments assumed. | F41: Recommendation | H41: Buy
B42: Interest Expense | C42: Interest expense projected at 5.79% of total debt (FY2026 actual effective rate); held constant (~₹28.57 Cr p.a.). | F42: Upside / (Downside) | G42: % | H42: =Model!M169 -> 0.38728737
B43: Equity Capital | C43: Equity capital held constant at ₹40.42 Cr; no dilution or buybacks modelled.
B44: Shares Outstanding | C44: Shares outstanding held constant at 40.42 crore throughout the forecast period.
B45: Non-Controlling Interest | C45: NCI held flat at FY2026 audited balance of ₹(3.12) Cr.
B46: Dividend Payout | C46: Dividend payout ratio fixed at 3.91% of net income; FY2022–FY2026 (5-year) average, as Star Cement paid no dividend in FY2022–FY2025.
B47: Associates P&L | C47: Not Applicable — Star Cement carries no separate share of profit/(loss) from associates; this line item does not appear in the model.
B48: DCF INPUTS
B49: Terminal Growth Rate | C49: Terminal growth rate of 4.00%; proxy for India's long-run nominal GDP floor.
B50: WACC | C50: Discount rate (WACC) of 10.96%; derived from CAPM cost of equity and after-tax cost of debt.
B51: Terminal Value — GGM | C51: Gordon Growth Model terminal value applied; FY2036 (undiscounted) terminal value of ₹21,644.38 Cr.
B52: Terminal Value — EV/EBITDA | C52: EV/EBITDA exit multiple of 15.43x (average of 8 large-cap listed cement peers) applied on FY2036 EBITDA; FY2036 (undiscounted) terminal value of ₹30,455.03 Cr.
B53: Terminal Value — Blended | C53: Final TV is the simple average of GGM and EV/EBITDA terminal values (₹28,071.97 Cr at FY2036), then discounted back via XNPV.
B54: Intrinsic Value | C54: Intrinsic value per share: ₹275.98 vs. CMP ₹198.94; implying +34% Upside. Recommendation: BUY.
B55: WACC COMPONENTS
B56: Risk-Free Rate | C56: 7.03%; 10-year Government of India G-Sec yield as of valuation date.
B57: Equity Risk Premium | C57: 4.53%; derived as equity market return (Nifty total-return proxy) minus risk-free rate.
B58: Levered Beta (Used) | C58: 1.021x; peer-average unlevered beta of 0.968 re-levered using Star Cement's own D/E of 7.34% and FY2026 effective tax rate of 25.56%.
B59: Cost of Equity (CAPM) | C59: 11.66%; derived as: Risk-Free Rate (7.03%) + Levered Beta (1.021) × Equity Risk Premium (4.53%).
B60: Pre-Tax Cost of Debt | C60: 5.79%; FY2026 actual interest expense divided by average total debt.
B61: After-Tax Cost of Debt | C61: 4.31%; pre-tax cost of debt × (1 − effective tax rate of 25.56%).
B62: COMPARABLE COMPANIES
B63: Peer Set | C63: 12 listed cement peers: UltraTech Cement, Grasim Industries, Ambuja Cements, Shree Cement, J K Cements, Dalmia Bharat, ACC, The Ramco Cement, JSW Cement, Nuvoco Vistas, India Cements, JK Lakshmi Cement.
B64: EV Calculation | C64: Peer EV = Market Cap + Total Debt − Cash & Equivalents; sourced from NSE/BSE filings.
B65: Valuation Multiples | C65: Sector median EV/EBITDA (16.13x) and P/E (36.37x) multiples used as relative valuation cross-checks.
B66: Exit Multiple | C66: Average EV/EBITDA of 15.43x across 8 large-cap cement peers (UltraTech, Grasim, Ambuja, Shree Cement, J K Cements, Dalmia Bharat, ACC, Ramco Cement) used as the terminal value exit multiple.
B67: SCENARIO ANALYSIS
B68: Scenarios Modelled | C68: Three scenarios: Base (13.00%), Bull (22.25%), Bear (7.5%) — Base and Bull taper at 10% p.a.; Bear tapers doen to 4%
B69: Scenario Differences | C69: Only top-line revenue growth rate differs across scenarios; all other assumptions are identical.
B70: Forecast Horizon | C70: 10-year explicit forecast period: FY2027–FY2036.

Sheet Historical
A1: Star Cements
A2: Historical Financial Information | E2: Units
H3: 2022 | I3: =H3+1 -> 2023 | J3: =I3+1 -> 2024 | K3: =J3+1 -> 2025 | L3: 2026
A4: Income Satement
D5: Particulars
D7: 1) INCOME
D8: a) Revenue from operations | E8: in cr | H8: 2221.819 | I8: 2704.8468 | J8: 2910.6671 | K8: 3163.3949 | L8: 3776.4873
D9: b) Other income | E9: in cr | H9: 33.3717 | I9: 52.0827 | J9: 26.4651 | K9: 10.5664 | L9: 19.2609
D10: Total Income | E10: in cr | H10: =SUM(H8:H9) -> 2255.1907 | I10: =SUM(I8:I9) -> 2756.9295 | J10: =SUM(J8:J9) -> 2937.1322 | K10: =SUM(K8:K9) -> 3173.9613 | L10: =SUM(L8:L9) -> 3795.7482
D11: 2) EXPENSES
D12: a) Cost of materials consumed | E12: in cr | H12: 545.4339 | I12: 643.5896 | J12: 462.9287 | K12: 566.2003 | L12: 496.0435
D13: b) Changes in inventories of finished goods and work-in-progress | E13: in cr | H13: 28.5413 | I13: -17.8632 | J13: 16.608 | K13: -47.0652 | L13: =(-19.79+23.21)/100 -> 0.0342
D14: c) Employee benefits expense | E14: in cr | H14: 159.3501 | I14: 195.8732 | J14: 214.7949 | K14: 247.4612 | L14: 277.2282
D15: d) Finance costs | E15: in cr | H15: 13.3403 | I15: 9.695 | J15: 12.6012 | K15: 31.6231 | L15: 46.3045
D16: e) Depreciation and amortisation expense | E16: in cr | H16: 121.6295 | I16: 131.1122 | J16: 146.5977 | K16: 331.9105 | L16: 365.2867
D17: f) Power and Fuel expense | E17: in cr | H17: 416.8999 | I17: 569.7349 | J17: 555.0974 | K17: 528.7884 | L17: 557.9056
D18: g) Carriage Outward expense | E18: in cr | H18: 427.0747 | I18: 506.7391 | J18: 741.4183 | K18: 828.3073 | L18: 1035.3812
D19: h) Other expenses | E19: in cr | H19: 302.1957 | I19: 350.982 | J19: 379.8926 | K19: 468.8346 | L19: 473.9433
D20: i) Captive Consumption of Cement | E20: in cr | H20: -2.9282 | I20: -12.6008 | J20: -16.3856 | K20: -7.773 | L20: 0
D21: Total expenses | E21: in cr | H21: =SUM(H12:H20) -> 2011.5372 | I21: =SUM(I12:I20) -> 2377.262 | J21: =SUM(J12:J20) -> 2513.5532 | K21: =SUM(K12:K20) -> 2948.2872 | L21: =SUM(L12:L20) -> 3252.1272
D22: 3) Profit before exceptional items and tax (1-2) | E22: in cr | H22: =H10-H21 -> 243.6535 | I22: =I10-I21 -> 379.6675 | J22: =J10-J21 -> 423.579 | K22: =K10-K21 -> 225.6741 | L22: =L10-L21 -> 543.621
D23: 4) Exceptional Items | E23: in cr | H23: 0 | I23: 0 | J23: 0 | K23: 0 | L23: 11.3197
D24: 5) Profit before tax (3-4) | E24: in cr | H24: =H22-H23 -> 243.6535 | I24: =I22-I23 -> 379.6675 | J24: =J22-J23 -> 423.579 | K24: =K22-K23 -> 225.6741 | L24: =L22-L23 -> 532.3013
D25: 6) Tax expenses | E25: in cr
D26: - Current tax | E26: in cr | H26: 39.5172 | I26: 67.2157 | J26: 78.5994 | K26: 59.8633 | L26: 101.7165
D27: - Deferred tax | E27: in cr | H27: -42.6139 | I27: 72.4451 | J27: 55.7229 | K27: -3.0115 | L27: 39.7322
D28: - Tax for earlier years | E28: in cr | H28: -0.0246 | I28: -7.5974 | J28: -5.8536 | K28: -0.0003 | L28: 0.3967
D29: Total tax expenses | E29: in cr | H29: =(SUM(H26:H28))/100 -> -0.031213 | I29: =(SUM(I26:I28))/100 -> 1.320634 | J29: =(SUM(J26:J28))/100 -> 1.284687 | K29: =(SUM(K26:K28))/100 -> 0.568515 | L29: =(SUM(L26:L28))/100 -> 1.418454
D30: 7) Profit for the year (5-6) | E30: in cr | H30: =H24-H29 -> 243.68471 | I30: =I24-I29 -> 378.34687 | J30: =J24-J29 -> 422.29431 | K30: =K24-K29 -> 225.10559 | L30: =L24-L29 -> 530.88285
D32: 10) Earnings per equity share (face value of ₹ 1 each)
D33: Basic (in ₹) | H33: 6.04 | I33: 6.13 | J33: 7.3 | K33: 4.18 | L33: 9.73
D34: Diluted (in ₹) | H34: 6.04 | I34: 6.13 | J34: 7.3 | K34: 4.18 | L34: 9.73
D35: Significant accounting policies
A37: Balancesheet
D39: Particulars
D40: A. Assets
D41: Non-current assets
D42: (a) Property, plant and equipment | E42: in cr | H42: 908.2913 | I42: 873.2595 | J42: 1396.4168 | K42: 2400.5821 | L42: 2589.2979
D43: (b) Capital work-in-progress | E43: in cr | H43: 104.5495 | I43: 550.62 | J43: 1019.0493 | K43: 219.8899 | L43: 94.7985
D44: (c) Right-of-use assets | E44: in cr | H44: 14.9187 | I44: 13.7007 | J44: 17.0336 | K44: 12.4551 | L44: 17.6
D45: (d) Intangible assets | E45: in cr | H45: 0.2625 | I45: 3.9812 | J45: 2.4769 | K45: 7.5037 | L45: 4.8841
D46: (e) Intangible assets under development | E46: in cr | H46: 4.5083 | I46: 0 | J46: 2.55 | K46: 0 | L46: 0
D47: (f) Financial assets | E47: in cr | H47: 0 | I47: 0 | J47: 0 | K47: 0 | L47: 0
D48: (i) Investments | E48: in cr | H48: 167.2675 | I48: 172.5493 | J48: 1.9875 | K48: 2.0222 | L48: 258.3626
D49: (ii) Loans | E49: in cr | H49: 0 | I49: 0 | J49: 17.1064 | K49: 15.4064 | L49: 17.2064
D50: (iii) Other financial assets | E50: in cr | H50: 122.824 | I50: 53.2571 | J50: 21.3586 | K50: 23.5103 | L50: 27.0245
D51: (g) Deferred tax assets (net) | E51: in cr | H51: 353.9201 | I51: 289.0396 | J51: 240.0834 | K51: 243.0868 | L51: 203.465
D52: (h) Non-current tax assets (net) | E52: in cr | H52: 11.079 | I52: 10.5731 | J52: 10.6012 | K52: 19.5088 | L52: 25.6768
D53: (i) Other non-current assets | E53: in cr | H53: 92.9857 | I53: 166.9932 | J53: 108.0114 | K53: 128.2243 | L53: 207.064
D54: Total non-current assets | E54: in cr | H54: =SUM(H42:H53) -> 1780.6066 | I54: =SUM(I42:I53) -> 2133.9737 | J54: =SUM(J42:J53) -> 2836.6751 | K54: =SUM(K42:K53) -> 3072.1896 | L54: =SUM(L42:L53) -> 3445.3798
D55: Current assets
D56: (a) Inventories | E56: in cr | H56: 195.2952 | I56: 374.1116 | J56: 334.9635 | K56: 446.3536 | L56: 465.6051
D57: (b) Financial assets
D58: (i) Trade receivables | E58: in cr | H58: 128.7492 | I58: 104.6911 | J58: 150.7779 | K58: 199.5409 | L58: 241.6488
D59: (ii) Cash and cash equivalents | E59: in cr | H59: 8.0755 | I59: 121.6223 | J59: 47.7869 | K59: 39.8463 | L59: 13.1363
D60: (iii) Other bank balances (other than (ii) above) | E60: in cr | H60: 376.5917 | I60: 190.1206 | J60: 49.5548 | K60: 12.5835 | L60: 111.5349
D61: (iv) Loans | E61: in cr | H61: 34.0977 | I61: 17.307 | J61: 3.25 | K61: 0.4 | L61: 0
D62: (v) Other financial assets | E62: in cr | H62: 132.7661 | I62: 41.054 | J62: 11.9177 | K62: 174.849 | L62: 188.2626
D63: (c) Other current assets | E63: in cr | H63: 88.9126 | I63: 148.5197 | J63: 167.447 | K63: 161.0862 | L63: 181.2895
D64: Total current assets | E64: in cr | H64: =SUM(H56:H63) -> 964.488 | I64: =SUM(I56:I63) -> 997.4263 | J64: =SUM(J56:J63) -> 765.6978 | K64: =SUM(K56:K63) -> 1034.6595 | L64: =SUM(L56:L63) -> 1201.4772
D65: Total assets | E65: in cr | H65: =SUM(H64,H54) -> 2745.0946 | I65: =SUM(I64,I54) -> 3131.4 | J65: =SUM(J64,J54) -> 3602.3729 | K65: =SUM(K64,K54) -> 4106.8491 | L65: =SUM(L64,L54) -> 4646.857
D66: B. Equity and liabilities
D67: Equity
D68: (a) Equity share capital | E68: in cr | H68: 40.418 | I68: 40.418 | J68: 40.418 | K68: 40.418 | L68: 40.418
D69: (b) Other equity | E69: in cr | H69: 2128.016 | I69: 2375.9576 | J69: 2669.6983 | K69: 2838.7768 | L69: 3150.7848
D70: (c) Non-controlling interest | E70: in cr | H70: 0 | I70: 0 | J70: - | K70: -0.2527 | L70: -3.1216
D71: Total Equity | E71: in cr | H71: =SUM(H68:H70) -> 2168.434 | I71: =SUM(I68:I70) -> 2416.3756 | J71: =SUM(J68:J70) -> 2710.1163 | K71: =SUM(K68:K70) -> 2878.9421 | L71: =SUM(L68:L70) -> 3188.0812
D72: Liabilities
D73: Non-current liabilities
D74: (a) Financial Liabilities
D75: (i) Borrowings | E75: in cr | H75: 8.0082 | I75: 4.8384 | J75: 72.1026 | K75: 292.729 | L75: 493.1861
D76: (ii) Lease liabilities | E76: in cr | H76: 155.7354 | I76: 166.6937 | J76: 12.6647 | K76: 7.1704 | L76: 9.1192
D77: (b) Provisions | E77: in cr | H77: 4.7933 | I77: 7.7253 | J77: 13.1788 | K77: 18.5642 | L77: 24.478
D78: (c) Other non current liabilities | E78: in cr | H78: 8.7713 | I78: 7.2718 | J78: 14.3174 | K78: 13.282 | L78: 12.4224
D79: Total Non-Current Liabilities | E79: in cr | H79: =SUM(H75:H78) -> 177.3082 | I79: =SUM(I75:I78) -> 186.5292 | J79: =SUM(J75:J78) -> 112.2635 | K79: =SUM(K75:K78) -> 331.7456 | L79: =SUM(L75:L78) -> 539.2057
D80: Current liabilities
D81: (a) Financial liabilities
D82: (i) Borrowings | E82: in cr | H82: 5.3778 | I82: 26.1035 | J82: 57.7264 | K82: 97.3643 | L82: 93.0011
D83: (ii) Lease liabilities | E83: in cr | H83: 2.2663 | I83: 4.4086 | J83: 4.4492 | K83: 5.4944 | L83: 8.0179
D84: (iii) Trade payables | E84: in cr | H84: 0 | I84: 0 | J84: 0 | K84: 0 | L84: 0
D85: (1) Total outstanding dues of micro enterprises and small enterprises | E85: in cr | H85: 4.9825 | I85: 9.4231 | J85: 37.0835 | K85: 54.958 | L85: 129.69
D86: (2) Total outstanding dues of trade payable other than micro enterprises and small enterprises | E86: in cr | H86: 207.471 | I86: 272.6193 | J86: 181.5787 | K86: 177.5829 | L86: 127.5176
D87: (iv) Other financial liabilities | E87: in cr | H87: 86.6258 | I87: 136.3938 | J87: 399.9596 | K87: 403.7102 | L87: 316.731
D88: (b) Other current liabilities | E88: in cr | H88: 88.8717 | I88: 76.4769 | J88: 92.9184 | K88: 152.6181 | L88: 240.4976
D89: (c) Provisions | E89: in cr | H89: 1.7886 | I89: 1.9758 | J89: 2.6174 | K89: 0.963 | L89: 1.1789
D90: (d) Current tax liabilities (net) | E90: in cr | H90: 1.9687 | I90: 1.0942 | J90: 3.6599 | K90: 3.4705 | L90: 2.936
D91: Total current liabilities | E91: in cr | H91: =SUM(H82:H90) -> 399.3524 | I91: =SUM(I82:I90) -> 528.4952 | J91: =SUM(J82:J90) -> 779.9931 | K91: =SUM(K82:K90) -> 896.1614 | L91: =SUM(L82:L90) -> 919.5701
D92: Total liabilities | E92: in cr | H92: =H91+H79 -> 576.6606 | I92: =I91+I79 -> 715.0244 | J92: =J91+J79 -> 892.2566 | K92: =K91+K79 -> 1227.907 | L92: =L91+L79 -> 1458.7758
D93: Total equity and liabilities | E93: in cr | H93: =H92+H71 -> 2745.0946 | I93: =I92+I71 -> 3131.4 | J93: =J92+J71 -> 3602.3729 | K93: =K92+K71 -> 4106.8491 | L93: =L92+L71 -> 4646.857
A99: Cashflow Statement
D101: Particulars
D102: A CASH FLOW FROM OPERATING ACTIVITIES | H102: 0 | I102: 0 | J102: 0 | K102: 0 | L102: 0
D103: Profit before tax | H103: 243.6535 | I103: 379.6675 | J103: 423.579 | K103: 225.6741 | L103: 543.621
D104: Adjustments for : | H104: 0 | I104: 0 | J104: 0 | K104: 0 | L104: 0
D105: Depreciation and amortisation expenses | H105: 119.0439 | I105: 128.9459 | J105: 141.7905 | K105: 326.9677 | L105: 358.4087
D106: Amortisation of right-of-use- assets | H106: 2.5856 | I106: 2.1663 | J106: 4.8072 | K106: 4.9428 | L106: 6.878
D107: Liability Written Back | H107: 0 | I107: 5.5029 | J107: -4.7076 | K107: -3.0214 | L107: -2.2607
D108: (Profit)/ Loss on Sale of Property, Plant and Equipment | H108: 0.0444 | I108: -0.0183 | J108: 1.1502 | K108: 0.1453 | L108: -0.1549
D109: Interest Income | H109: -33.1238 | I109: -43.3479 | J109: -19.5219 | K109: -3.2034 | L109: -11.6668
D110: Finance Costs | H110: 13.3403 | I110: 9.695 | J110: 12.6012 | K110: 31.6231 | L110: 46.3045
...

Sheet Model
A1: Star Cements | H1: Historical Period | M1: Forcasted Period
A2: Financial Statement and Analysis | F2: Units | H2: 2022 | I2: =H2+1 -> 2023 | J2: =I2+1 -> 2024 | K2: =J2+1 -> 2025 | L2: =K2+1 -> 2026 | M2: 2027 | N2: =M2+1 -> 2028 | O2: =N2+1 -> 2029 | P2: =O2+1 -> 2030 | Q2: =P2+1 -> 2031 | R2: =Q2+1 -> 2032 | S2: =R2+1 -> 2033 | T2: =S2+1 -> 2034 | U2: =T2+1 -> 2035 | V2: =U2+1 -> 2036
A4: Ratios & Assumptions
D6: Live Scenario | E6: Base Case | F6: Units
D7: Revenue(Growth) | F7: % | I7: =I23/H23-1 -> 0.22248176 | J7: =J23/I23-1 -> 0.06536355 | K7: =K23/J23-1 -> 0.080632768 | L7: =L23/K23-1 -> 0.19590248 | M7: {=_xlfn.XLOOKUP(E6,'Scenario Analysis'!D5:D7,'Scenario Analysis'!H5:Q7)} -> 0.13 | N7: 0.117 | O7: 0.1053 | P7: 0.09477 | Q7: 0.085293 | R7: 0.0767637 | S7: 0.06908733 | T7: 0.062178597 | U7: 0.055960737 | V7: 0.050364664
D8: Cost of Goood Sold (% of Revenue) | F8: % | H8: =-H24/H23 -> 0.24185711 | I8: =-I24/I23 -> 0.23344434 | J8: =-J24/J23 -> 0.15761248 | K8: =-K24/K23 -> 0.17838916 | L8: =-L24/L23 -> 0.13068398 | M8: =AVERAGE(J8:L8) -> 0.15556188 | N8: =M8 -> 0.15556188 | O8: =N8 -> 0.15556188 | P8: =O8 -> 0.15556188 | Q8: =P8 -> 0.15556188 | R8: =Q8 -> 0.15556188 | S8: =R8 -> 0.15556188 | T8: =S8 -> 0.15556188 | U8: =T8 -> 0.15556188 | V8: =U8 -> 0.15556188
D9: Salaries and Benefits (% of Revenue) | F9: % | H9: =-H27/H23 -> 0.070659257 | I9: =-I27/I23 -> 0.071047591 | J9: =-J27/J23 -> 0.073130825 | K9: =-K27/K23 -> 0.077966042 | L9: =-L27/L23 -> 0.07303651 | M9: =AVERAGE(H9:L9) -> 0.073168045 | N9: =M9 -> 0.073168045 | O9: =N9 -> 0.073168045 | P9: =O9 -> 0.073168045 | Q9: =P9 -> 0.073168045 | R9: =Q9 -> 0.073168045 | S9: =R9 -> 0.073168045 | T9: =S9 -> 0.073168045 | U9: =T9 -> 0.073168045 | V9: =U9 -> 0.073168045
D10: Other SG&A Expenses (% of Revenue) | F10: % | H10: =-H28/H23 -> 0.51959393 | I10: =-I28/I23 -> 0.50672025 | J10: =-J28/J23 -> 0.57083937 | K10: =-K28/K23 -> 0.55800684 | L10: =-L28/L23 -> 0.5446263 | M10: =AVERAGE(H10:L10) -> 0.53995734 | N10: =M10 -> 0.53995734 | O10: =N10 -> 0.53995734 | P10: =O10 -> 0.53995734 | Q10: =P10 -> 0.53995734 | R10: =Q10 -> 0.53995734 | S10: =R10 -> 0.53995734 | T10: =S10 -> 0.53995734 | U10: =T10 -> 0.53995734 | V10: =U10 -> 0.53995734
D11: Depreciation and amortisation expense (% of PP&E) | F11: % | I11: =-I30/H51 -> 0.14435039 | J11: =-J30/I51 -> 0.16787415 | K11: =-K30/J51 -> 0.23768727 | L11: =-L30/K51 -> 0.15216589 | M11: =L11 -> 0.15216589 | N11: =M11 -> 0.15216589 | O11: =N11 -> 0.15216589 | P11: =O11+2% -> 0.17216589 | Q11: =P11 -> 0.17216589 | R11: =Q11 -> 0.17216589 | S11: =R11+2% -> 0.19216589 | T11: =S11 -> 0.19216589 | U11: =T11 -> 0.19216589 | V11: =U11+2% -> 0.21216589
D12: Interest Expenses (% of Debt) | F12: % | I12: =-I32/(H65+H62) -> 0.094790576 | J12: =-J32/(I65+I62) -> 0.073371867 | K12: =-K32/(J65+J62) -> 0.059192929 | L12: =-L32/(K65+K62) -> 0.057931467 | M12: =L12 -> 0.057931467 | N12: =M12 -> 0.057931467 | O12: =N12 -> 0.057931467 | P12: =O12 -> 0.057931467 | Q12: =P12 -> 0.057931467 | R12: =Q12 -> 0.057931467 | S12: =R12 -> 0.057931467 | T12: =S12 -> 0.057931467 | ... V12: =U12 -> 0.057931467
D13: Taxes (% of Earnings before Tax) | F13: % | H13: =-H36/H35 -> -0.012810405 | I13: =-I36/I35 -> 0.34783962 | J13: =-J36/J35 -> 0.30329336 | K13: =-K36/K35 -> 0.25191859 | L13: =-L36/L35 -> 0.25560461 | M13: =L13 -> 0.25560461 | N13: =M13+0.5% -> 0.26060461 | O13: =N13 -> 0.26060461 | P13: =O13+0.5% -> 0.26560461 | Q13: =P13 -> 0.26560461 | R13: =Q13+0.5% -> 0.27060461 | S13: =R13 -> 0.27060461 | T13: =S13+0.5% -> 0.27560461 | U13: =T13 -> 0.27560461 | V13: =U13+0.5% -> 0.28060461
D14: Dividend Payout | F14: % | H14: =-H102/H37 -> 0 | I14: =-I102/I37 -> 0 | J14: =-J102/J37 -> 0 | K14: =-K102/K37 -> 0 | L14: =-L102/L37 -> 0.1956839 | M14: =AVERAGE(H14:L14) -> 0.03913678 | N14: =M14 -> 0.03913678 | O14: =N14 -> 0.03913678 | P14: =O14 -> 0.03913678 | Q14: =P14 -> 0.03913678 | R14: =Q14 -> 0.03913678 | S14: =R14 -> 0.03913678 | T14: =S14 -> 0.03913678 | U14: =T14 -> 0.03913678 | V14: =U14 -> 0.03913678
D15: Accounts Recievables DSO | F15: Days | I15: =AVERAGE(I45,H45)/I23*365 -> 15.453008 | J15: =AVERAGE(J45,I45)/J23*365 -> 15.873679 | K15: =AVERAGE(K45,J45)/K23*365 -> 20.143025 | L15: =AVERAGE(L45,K45)/L23*365 -> 21.21245 | M15: =AVERAGE(I15:L15) -> 18.170541 | N15: =M15 -> 18.170541 | O15: =N15 -> 18.170541 | P15: =O15 -> 18.170541 | Q15: =P15 -> 18.170541 | R15: =Q15 -> 18.170541 | S15: =R15 -> 18.170541 | T15: =S15 -> 18.170541 | U15: =T15 -> 18.170541 | V15: =U15 -> 18.170541
D16: Inventory DIO | F16: Days | I16: =-AVERAGE(I47,H47)/I24*365 -> 161.46429 | J16: =-AVERAGE(J47,I47)/J24*365 -> 279.53809 | K16: =-AVERAGE(K47,J47)/K24*365 -> 251.83733 | L16: =-AVERAGE(L47,K47)/L24*365 -> 335.51989 | M16: =AVERAGE(I16:L16) -> 257.0899 | N16: =M16 -> 257.0899 | O16: =N16 -> 257.0899 | P16: =O16 -> 257.0899 | Q16: =P16 -> 257.0899 | R16: =Q16 -> 257.0899 | S16: =R16 -> 257.0899 | T16: =S16 -> 257.0899 | U16: =T16 -> 257.0899 | V16: =U16 -> 257.0899
D17: Accounts Payables DPO | F17: Days | I17: =-AVERAGE(H61,I61)/I24*365 -> 140.22213 | J17: =-AVERAGE(I61,J61)/J24*365 -> 197.39236 | K17: =-AVERAGE(J61,K61)/K24*365 -> 145.43363 | L17: =-AVERAGE(K61,L61)/L24*365 -> 180.184 | M17: =AVERAGE(I17:L17) -> 165.80803 | N17: =M17 -> 165.80803 | O17: =N17 -> 165.80803 | P17: =O17 -> 165.80803 | Q17: =P17 -> 165.80803 | R17: =Q17 -> 165.80803 | S17: =R17 -> 165.80803 | T17: =S17 -> 165.80803 | U17: =T17 -> 165.80803 | V17: =U17 -> 165.80803
D18: Capex/ Revenue | F18: Times | H18: =H121/H23 -> 0 | I18: =I121/I23 -> 0.03485051 | J18: =J121/J23 -> 0.22803025 | K18: =K121/K23 -> 0.42094899 | L18: =L121/L23 -> 0.14595344 | M18: 0.13745357 | N18: 0.28226001 | O18: 0.21528376 | P18: =AVERAGE(I18:O18) -> 0.20925436 | Q18: =P18-0.03 -> 0.17925436 | R18: =Q18-0.03 -> 0.14925436 | S18: =R18-0.03 -> 0.11925436 | T18: =S18-0.03 -> 0.089254361 | U18: =T18-0.03 -> 0.059254361 | V18: =U18-0.03 -> 0.029254361
D19: Investments as % of total Assets | F19: % | H19: =H48/H57 -> 0.048364854 | I19: =I48/I57 -> 0.01311043 | J19: =J48/J57 -> 0.0033082916 | K19: =K48/K57 -> 0.042574976 | L19: =L48/L57 -> 0.040513965 | M19: =M48/M57 -> 0.036913175 | N19: =N48/N57 -> 0.033608747 | O19: =O48/O57 -> 0.030934956 | ... V19: =V48/V57 -> 0.018896865
A21: Income Statement | H21: 2022 | I21: =H21+1 -> 2023 | J21: =I21+1 -> 2024 | K21: =J21+1 -> 2025 | L21: =K21+1 -> 2026 | M21: =L21+1 -> 2027 | N21: =M21+1 -> 2028 | O21: =N21+1 -> 2029 | P21: =O21+1 -> 2030 | ... V21: =U21+1 -> 2036
B22: Income
D23: Revenue | F23: ₹ in Cr | H23: =Historical!H10 -> 2255.1907 | I23: =Historical!I10 -> 2756.9295 | J23: =Historical!J10 -> 2937.1322 | K23: =Historical!K10 -> 3173.9613 | L23: =Historical!L10 -> 3795.7482 | M23: =L23*(1+M7) -> 4289.1955 | N23: =M23*(1+N7) -> 4791.0313 | O23: =N23*(1+O7) -> 5295.5269 | P23: =O23*(1+P7) -> 5797.384 | Q23: =P23*(1+Q7) -> 6291.8603 | R23: =Q23*(1+R7) -> 6774.8468 | S23: =R23*(1+S7) -> 7242.9028 | T23: =S23*(1+T7) -> 7693.2564 | ... V23: =U23*(1+V7) -> 8532.928
D24: Cost of Goood Sold(COGS) | F24: ₹ in Cr | H24: =-Historical!H12 -> -545.4339 | I24: =-Historical!I12 -> -643.5896 | J24: =-Historical!J12 -> -462.9287 | K24: =-Historical!K12 -> -566.2003 | L24: =-Historical!L12 -> -496.0435 | M24: =-M23*M8 -> -667.2353 | N24: =-N23*N8 -> -745.30183 | O24: =-O23*O8 -> -823.78211 | P24: =-P23*P8 -> -901.85194 | Q24: =-Q23*Q8 -> -978.7736 | R24: =-R23*R8 -> -1053.9079 | S24: =-S23*S8 -> -1126.7196 | T24: =-T23*T8 -> -1196.7774 | ... V24: =-V23*V8 -> -1327.3983
D25: Gross Profit | F25: ₹ in Cr | H25: =SUM(H23:H24) -> 1709.7568 | I25: =SUM(I23:I24) -> 2113.3399 | J25: =SUM(J23:J24) -> 2474.2035 | K25: =SUM(K23:K24) -> 2607.761 | L25: =SUM(L23:L24) -> 3299.7047 | M25: =SUM(M23:M24) -> 3621.9602 | N25: =SUM(N23:N24) -> 4045.7295 | O25: =SUM(O23:O24) -> 4471.7448 | ... V25: =SUM(V23:V24) -> 7205.5297
C26: Expense
D27: Salalries and Benefits | F27: ₹ in Cr | H27: =-Historical!H14 -> -159.3501 | I27: =-Historical!I14 -> -195.8732 | J27: =-Historical!J14 -> -214.7949 | K27: =-Historical!K14 -> -247.4612 | L27: =-Historical!L14 -> -277.2282 | M27: =-M23*M9 -> -313.83205 | N27: =-N23*N9 -> -350.5504 | O27: =-O23*O9 -> -387.46335 | P27: =-P23*P9 -> -424.18325 | Q27: =-Q23*Q9 -> -460.36312 | R27: =-R23*R9 -> -495.70229 | S27: =-S23*S9 -> -529.94904 | T27: =-T23*T9 -> -562.90053 | ... V27: =-V23*V9 -> -624.33766
D28: Other SG&A Expenses | F28: ₹ in Cr | H28: =-SUM(Historical!H13,Historical!H17:H20) -> -1171.7834 | I28: =-SUM(Historical!I13,Historical!I17:I20) -> -1396.992 | J28: =-SUM(Historical!J13,Historical!J17:J20) -> -1676.6307 | K28: =-SUM(Historical!K13,Historical!K17:K20) -> -1771.0921 | L28: =-SUM(Historical!L13,Historical!L17:L20) -> -2067.2643 | M28: =M23*-M10 -> -2315.9826 | N28: =N23*-N10 -> -2586.9525 | O28: =O23*-O10 -> -2859.3586 | P28: =P23*-P10 -> -3130.34 | Q28: =Q23*-Q10 -> -3397.3361 | R28: =R23*-R10 -> -3658.1282 | S28: =S23*-S10 -> -3910.8585 | T28: =T23*-T10 -> -4154.0302 | ... V28: =V23*-V10 -> -4607.4171
D29: EBITDA | F29: ₹ in Cr | H29: =SUM(H25:H28) -> 378.6233 | I29: =SUM(I25:I28) -> 520.4747 | J29: =SUM(J25:J28) -> 582.7779 | K29: =SUM(K25:K28) -> 589.2077 | L29: =SUM(L25:L28) -> 955.2122 | M29: =SUM(M25:M28) -> 992.14556 | N29: =SUM(N25:N28) -> 1108.2266 | O29: =SUM(O25:O28) -> 1224.9228 | ... V29: =SUM(V25:V28) -> 1973.775
D30: Depriciation and Amortization Expense | F30: ₹ in Cr | H30: =-Historical!H16 -> -121.6295 | I30: =-Historical!I16 -> -131.1122 | J30: =-Historical!J16 -> -146.5977 | K30: =-Historical!K16 -> -331.9105 | L30: =-Historical!L16 -> -365.2867 | M30: =M11*-L51 -> -394.00281 | N30: =N11*-M51 -> -423.76073 | O30: =O11*-N51 -> -565.05525 | P30: =P11*-O51 -> -738.3165 | Q30: =Q11*-P51 -> -820.06282 | R30: =R11*-Q51 -> -873.05214 | S30: =S11*-R51 -> -1001.0146 | T30: =T11*-S51 -> -974.63659 | ... V30: =V11*-U51 -> -922.06081
D31: EBIT | F31: ₹ in Cr | H31: =SUM(H29:H30) -> 256.9938 | I31: =SUM(I29:I30) -> 389.3625 | J31: =SUM(J29:J30) -> 436.1802 | K31: =SUM(K29:K30) -> 257.2972 | L31: =SUM(L29:L30) -> 589.9255 | M31: =SUM(M29:M30) -> 598.14275 | N31: =SUM(N29:N30) -> 684.46586 | O31: =SUM(O29:O30) -> 659.8676 | ... V31: =SUM(V29:V30) -> 1051.7141
D32: Finance Cost | F32: ₹ in Cr | H32: =-Historical!H15 -> -13.3403 | I32: =-Historical!I15 -> -9.695 | J32: =-Historical!J15 -> -12.6012 | K32: =-Historical!K15 -> -31.6231 | L32: =-Historical!L15 -> -46.3045 | M32: =M12*-AVERAGE(M126,M128) -> -28.570994 | N32: =N12*-M65 -> -28.570994 | O32: =O12*-N65 -> -28.570994 | P32: =P12*-O65 -> -28.570994 | Q32: =Q12*-P65 -> -28.570994 | R32: =R12*-Q65 -> -28.570994 | S32: =S12*-R65 -> -28.570994 | T32: =T12*-S65 -> -28.570994 | U32: =U12*-T65 -> -28.570994 | V32: =V12*-U65 -> -28.570994
D33: Profit before exceptional items and tax | F33: ₹ in Cr | H33: =SUM(H31:H32) -> 243.6535 | I33: =SUM(I31:I32) -> 379.6675 | J33: =SUM(J31:J32) -> 423.579 | K33: =SUM(K31:K32) -> 225.6741 | L33: =SUM(L31:L32) -> 543.621 | M33: =M31+M32 -> 569.57176 | N33: =N31+N32 -> 655.89486 | O33: =O31+O32 -> 631.2966 | P33: =P31+P32 -> 574.1213 | Q33: =Q31+Q32 -> 606.75363 | R33: =R31+R32 -> 665.48524 | S33: =S31+S32 -> 645.79012 | T33: =T31+T32 -> 776.34063 | ... V33: =V31+V32 -> 1023.1431
D34: Exceptional Items | F34: ₹ in Cr | H34: =Historical!H23 -> 0 | I34: =Historical!I23 -> 0 | J34: =Historical!J23 -> 0 | K34: =Historical!K23 -> 0 | L34: =Historical!L23 -> 11.3197 | M34: 0 | N34: 0 | O34: 0 | P34: 0 | Q34: 0 | R34: 0 | S34: 0 | T34: 0 | U34: 0 | V34: 0
D35: Earnings Before Tax | F35: ₹ in Cr | H35: =SUM(H33:H34) -> 243.6535 | I35: =SUM(I33:I34) -> 379.6675 | J35: =SUM(J33:J34) -> 423.579 | K35: =SUM(K33:K34) -> 225.6741 | L35: =SUM(L33:L34) -> 554.9407 | M35: =SUM(M33:M34) -> 569.57176 | N35: =SUM(N33:N34) -> 655.89486 | O35: =SUM(O33:O34) -> 631.2966 | ... V35: =SUM(V33:V34) -> 1023.1431
D36: Taxes | F36: ₹ in Cr | H36: =-SUM(Historical!H26:H28) -> 3.1213 | I36: =-SUM(Historical!I26:I28) -> -132.0634 | J36: =-SUM(Historical!J26:J28) -> -128.4687 | K36: =-SUM(Historical!K26:K28) -> -56.8515 | L36: =-SUM(Historical!L26:L28) -> -141.8454 | M36: =-(M13)*M35 -> -145.58517 | N36: =-(N13)*N35 -> -170.92922 | O36: =-(O13)*O35 -> -164.5188 | P36: =-(P13)*P35 -> -152.48926 | Q36: =-(Q13)*Q35 -> -161.15656 | R36: =-(R13)*R35 -> -180.08337 | S36: =-(S13)*S35 -> -174.75378 | T36: =-(T13)*T35 -> -213.96306 | ... V36: =-(V13)*V35 -> -287.09868
D37: Net Earnings | F37: ₹ in Cr | H37: =SUM(H35:H36) -> 246.7748 | I37: =SUM(I35:I36) -> 247.6041 | J37: =SUM(J35:J36) -> 295.1103 | K37: =SUM(K35:K36) -> 168.8226 | L37: =SUM(L35:L36) -> 413.0953 | M37: =SUM(M35:M36) -> 423.98659 | N37: =SUM(N35:N36) -> 484.96564 | O37: =SUM(O35:O36) -> 466.7778 | ... V37: =SUM(V35:V36) -> 736.04446
A39: Balancesheet
B41: Assets
C42: Current Assets
D43: Cash | F43: ₹ in Cr | H43: =Historical!H59 -> 8.0755 | I43: =Historical!I59 -> 121.6223 | J43: =Historical!J59 -> 47.7869 | K43: =Historical!K59 -> 39.8463 | L43: =Historical!L59 -> 13.1363 | M43: =M107 -> 294.62019 | N43: =N107 -> -212.45596 | O43: =O107 -> -383.67394 | P43: =P107 -> -497.86249 | Q43: =Q107 -> -421.33853 | R43: =R107 -> -135.89133 | S43: =S107 -> 412.46682 | T43: =T107 -> 1200.8744 | ... V43: =V107 -> 3592.2105
D44: Bank Deposits | F44: ₹ in Cr | H44: =Historical!H60 -> 376.5917 | I44: =Historical!I60 -> 190.1206 | J44: =Historical!J60 -> 49.5548 | K44: =Historical!K60 -> 12.5835 | L44: =Historical!L60 -> 111.5349 | M44: =L44 -> 111.5349 | N44: =M44 -> 111.5349 | O44: =N44 -> 111.5349 | P44: =O44 -> 111.5349 | Q44: =P44 -> 111.5349 | R44: =Q44 -> 111.5349 | S44: =R44 -> 111.5349 | T44: =S44 -> 111.5349 | ... V44: =U44 -> 111.5349
D45: Accounts Receivables | F45: ₹ in Cr | H45: =Historical!H58 -> 128.7492 | I45: =Historical!I58 -> 104.6911 | J45: =Historical!J58 -> 150.7779 | K45: =Historical!K58 -> 199.5409 | L45: =Historical!L58 -> 241.6488 | M45: =M15*M23/365 -> 213.52603 | N45: =N15*N23/365 -> 238.50857 | O45: =O15*O23/365 -> 263.62353 | P45: =P15*P23/365 -> 288.60713 | Q45: =Q15*Q23/365 -> 313.22329 | R45: =R15*R23/365 -> 337.26747 | S45: =S15*S23/365 -> 360.56838 | T45: =T15*T23/365 -> 382.98802 | ... V45: =V15*V23/365 -> 424.7888
D46: Loan Recievables | F46: ₹ in Cr | H46: =Historical!H61 -> 34.0977 | I46: =Historical!I61 -> 17.307 | J46: =Historical!J61 -> 3.25 | K46: =Historical!K61 -> 0.4 | L46: =Historical!L61 -> 0 | M46: =L46 -> 0 | N46: =M46 -> 0 | O46: =N46 -> 0 | P46: =O46 -> 0 | Q46: =P46 -> 0 | R46: =Q46 -> 0 | S46: =R46 -> 0 | T46: =S46 -> 0 | ... V46: =U46 -> 0
D47: Inventory | F47: ₹ in Cr | H47: =Historical!H56 -> 195.2952 | I47: =Historical!I56 -> 374.1116 | J47: =Historical!J56 -> 334.9635 | K47: =Historical!K56 -> 446.3536 | L47: =Historical!L56 -> 465.6051 | M47: =M16*-M24/365 -> 469.97112 | N47: =N16*-N24/365 -> 524.95774 | O47: =O16*-O24/365 -> 580.23579 | P47: =P16*-P24/365 -> 635.22473 | Q47: =Q16*-Q24/365 -> 689.40496 | R47: =R16*-R24/365 -> 742.32623 | S47: =S16*-S24/365 -> 793.61157 | T47: =T16*-T24/365 -> 842.95722 | ... V47: =V16*-V24/365 -> 934.96081
D48: Investments | F48: ₹ in Cr | H48: =Historical!H62 -> 132.7661 | I48: =Historical!I62 -> 41.054 | J48: =Historical!J62 -> 11.9177 | K48: =Historical!K62 -> 174.849 | L48: =Historical!L62 -> 188.2626 | M48: =L48 -> 188.2626 | N48: =M48 -> 188.2626 | O48: =N48 -> 188.2626 | P48: =O48 -> 188.2626 | Q48: =P48 -> 188.2626 | R48: =Q48 -> 188.2626 | S48: =R48 -> 188.2626 | T48: =S48 -> 188.2626 | ... V48: =U48 -> 188.2626
D49: Other Current Assets | F49: ₹ in Cr | H49: =Historical!H63 -> 88.9126 | I49: =Historical!I63 -> 148.5197 | J49: =Historical!J63 -> 167.447 | K49: =Historical!K63 -> 161.0862 | L49: =Historical!L63 -> 181.2895 | M49: =L49 -> 181.2895 | N49: =M49 -> 181.2895 | O49: =N49 -> 181.2895 | P49: =O49 -> 181.2895 | Q49: =P49 -> 181.2895 | R49: =Q49 -> 181.2895 | S49: =R49 -> 181.2895 | T49: =S49 -> 181.2895 | ... V49: =U49 -> 181.2895
C50: Non-Current Assets
D51: Property & Equiipments | F51: ₹ in Cr | H51: =Historical!H42 -> 908.2913 | I51: =Historical!I42 -> 873.2595 | J51: =Historical!J42 -> 1396.4168 | K51: =Historical!K42 -> 2400.5821 | L51: =Historical!L42 -> 2589.2979 | M51: =M123 -> 2784.8603 | N51: =N123 -> 3713.4161 | O51: =O123 -> 4288.4018 | P51: =P123 -> 4763.2132 | Q51: =Q123 -> 5070.9938 | R51: =R123 -> 5209.1171 | S51: =S123 -> 5071.8503 | T51: =T123 -> 4783.8703 | ... V51: =V123 -> 3673.5074
D52: Capital work-in-progress | F52: ₹ in Cr | H52: =Historical!H43 -> 104.5495 | I52: =Historical!I43 -> 550.62 | J52: =Historical!J43 -> 1019.0493 | K52: =Historical!K43 -> 219.8899 | L52: =Historical!L43 -> 94.7985 | M52: =L52 -> 94.7985 | N52: =M52 -> 94.7985 | O52: =N52 -> 94.7985 | P52: =O52 -> 94.7985 | Q52: =P52 -> 94.7985 | R52: =Q52 -> 94.7985 | S52: =R52 -> 94.7985 | T52: =S52 -> 94.7985 | ... V52: =U52 -> 94.7985
D53: Financial Assets | F53: ₹ in Cr | H53: =SUM(Historical!H48:H50) -> 290.0915 | I53: =SUM(Historical!I48:I50) -> 225.8064 | J53: =SUM(Historical!J48:J50) -> 40.4525 | K53: =SUM(Historical!K48:K50) -> 40.9389 | L53: =SUM(Historical!L48:L50) -> 302.5935 | M53: =L53 -> 302.5935 | N53: =M53 -> 302.5935 | O53: =N53 -> 302.5935 | P53: =O53 -> 302.5935 | Q53: =P53 -> 302.5935 | R53: =Q53 -> 302.5935 | S53: =R53 -> 302.5935 | T53: =S53 -> 302.5935 | ... V53: =U53 -> 302.5935
D54: Deffered Tax Assets | H54: =SUM(Historical!H51:H52) -> 364.9991 | I54: =SUM(Historical!I51:I52) -> 299.6127 | J54: =SUM(Historical!J51:J52) -> 250.6846 | K54: =SUM(Historical!K51:K52) -> 262.5956 | L54: =SUM(Historical!L51:L52) -> 229.1418 | M54: =L54 -> 229.1418 | N54: =M54 -> 229.1418 | O54: =N54 -> 229.1418 | P54: =O54 -> 229.1418 | Q54: =P54 -> 229.1418 | R54: =Q54 -> 229.1418 | S54: =R54 -> 229.1418 | T54: =S54 -> 229.1418 | ... V54: =U54 -> 229.1418
D55: Intangible Assets | F55: ₹ in Cr | H55: =SUM(Historical!H44:H46) -> 19.6895 | I55: =SUM(Historical!I44:I46) -> 17.6819 | J55: =SUM(Historical!J44:J46) -> 22.0605 | K55: =SUM(Historical!K44:K46) -> 19.9588 | L55: =SUM(Historical!L44:L46) -> 22.4841 | M55: =L55 -> 22.4841 | N55: =M55 -> 22.4841 | O55: =N55 -> 22.4841 | P55: =O55 -> 22.4841 | Q55: =P55 -> 22.4841 | R55: =Q55 -> 22.4841 | S55: =R55 -> 22.4841 | T55: =S55 -> 22.4841 | ... V55: =U55 -> 22.4841
D56: Other Non Current Assets | F56: ₹ in Cr | H56: =Historical!H53 -> 92.9857 | I56: =Historical!I53 -> 166.9932 | J56: =Historical!J53 -> 108.0114 | K56: =Historical!K53 -> 128.2243 | L56: =Historical!L53 -> 207.064 | M56: =L56 -> 207.064 | N56: =M56 -> 207.064 | O56: =N56 -> 207.064 | P56: =O56 -> 207.064 | Q56: =P56 -> 207.064 | R56: =Q56 -> 207.064 | S56: =R56 -> 207.064 | T56: =S56 -> 207.064 | ... V56: =U56 -> 207.064
D57: Total Assets | F57: ₹ in Cr | H57: =SUM(H43:H56) -> 2745.0946 | I57: =SUM(I43:I56) -> 3131.4 | J57: =SUM(J43:J56) -> 3602.3729 | K57: =SUM(K43:K56) -> 4106.8491 | L57: =SUM(L43:L56) -> 4646.857 | M57: =SUM(M43:M56) -> 5100.1465 | N57: =SUM(N43:N56) -> 5601.5954 | O57: =SUM(O43:O56) -> 6085.7561 | ... V57: =SUM(V43:V56) -> 9962.6365
B59: Liabilities
C60: Current Liabilities
D61: Accounts Payables | F61: ₹ in Cr | H61: =SUM(Historical!H85:H86) -> 212.4535 | I61: =SUM(Historical!I85:I86) -> 282.0424 | J61: =SUM(Historical!J85:J86) -> 218.6622 | K61: =SUM(Historical!K85:K86) -> 232.5409 | L61: =SUM(Historical!L85:L86) -> 257.2076 | M61: =M17*M24/-365 -> 303.10403 | N61: =N17*N24/-365 -> 338.5672 | O61: =O17*O24/-365 -> 374.21832 | P61: =P17*P24/-365 -> 409.68299 | Q61: =Q17*Q24/-365 -> 444.62609 | R61: =R17*R24/-365 -> 478.75723 | S61: =S17*S24/-365 -> 511.83329 | T61: =T17*T24/-365 -> 543.65836 | ... V61: =V17*V24/-365 -> 602.99533
D62: Other Current Financial Liabilities | H62: =SUM(Historical!H82:H83,Historical!H87) -> 94.2699 | I62: =SUM(Historical!I82:I83,Historical!I87) -> 166.9059 | J62: =SUM(Historical!J82:J83,Historical!J87) -> 462.1352 | K62: =SUM(Historical!K82:K83,Historical!K87) -> 506.5689 | L62: =SUM(Historical!L82:L83,Historical!L87) -> 417.75 | M62: =L62 -> 417.75 | N62: =M62 -> 417.75 | O62: =N62 -> 417.75 | P62: =O62 -> 417.75 | Q62: =P62 -> 417.75 | R62: =Q62 -> 417.75 | S62: =R62 -> 417.75 | T62: =S62 -> 417.75 | ... V62: =U62 -> 417.75
D63: Other Current Liabilities | F63: ₹ in Cr | H63: =SUM(Historical!H88:H90) -> 92.629 | I63: =SUM(Historical!I88:I90) -> 79.5469 | J63: =SUM(Historical!J88:J90) -> 99.1957 | K63: =SUM(Historical!K88:K90) -> 157.0516 | L63: =SUM(Historical!L88:L90) -> 244.6125 | M63: =L63 -> 244.6125 | N63: =M63 -> 244.6125 | O63: =N63 -> 244.6125 | P63: =O63 -> 244.6125 | Q63: =P63 -> 244.6125 | R63: =Q63 -> 244.6125 | S63: =R63 -> 244.6125 | T63: =S63 -> 244.6125 | ... V63: =U63 -> 244.6125
C64: Non-Current Liabilities
D65: Debt | F65: ₹ in Cr | H65: =Historical!H75 -> 8.0082 | I65: =Historical!I75 -> 4.8384 | J65: =Historical!J75 -> 72.1026 | K65: =Historical!K75 -> 292.729 | L65: =Historical!L75 -> 493.1861 | M65: =M128 -> 493.1861 | N65: =N128 -> 493.1861 | O65: =O128 -> 493.1861 | P65: =P128 -> 493.1861 | Q65: =Q128 -> 493.1861 | R65: =R128 -> 493.1861 | S65: =S128 -> 493.1861 | T65: =T128 -> 493.1861 | ... V65: =V128 -> 493.1861
D66: Lease Liabilities | H66: =Historical!H76 -> 155.7354 | I66: =Historical!I76 -> 166.6937 | J66: =Historical!J76 -> 12.6647 | K66: =Historical!K76 -> 7.1704 | L66: =Historical!L76 -> 9.1192 | M66: =L66 -> 9.1192 | N66: =M66 -> 9.1192 | O66: =N66 -> 9.1192 | P66: =O66 -> 9.1192 | Q66: =P66 -> 9.1192 | R66: =Q66 -> 9.1192 | S66: =R66 -> 9.1192 | T66: =S66 -> 9.1192 | ... V66: =U66 -> 9.1192
D67: Provisions | H67: =Historical!H77 -> 4.7933 | I67: =Historical!I77 -> 7.7253 | J67: =Historical!J77 -> 13.1788 | K67: =Historical!K77 -> 18.5642 | L67: =Historical!L77 -> 24.478 | M67: =L67 -> 24.478 | N67: =M67 -> 24.478 | O67: =N67 -> 24.478 | P67: =O67 -> 24.478 | Q67: =P67 -> 24.478 | R67: =Q67 -> 24.478 | S67: =R67 -> 24.478 | T67: =S67 -> 24.478 | ... V67: =U67 -> 24.478
D68: Other Non Current Liabilities | F68: ₹ in Cr | H68: =Historical!H78 -> 8.7713 | I68: =Historical!I78 -> 7.2718 | J68: =Historical!J78 -> 14.3174 | K68: =Historical!K78 -> 13.282 | L68: =Historical!L78 -> 12.4224 | M68: =L68 -> 12.4224 | N68: =M68 -> 12.4224 | O68: =N68 -> 12.4224 | P68: =O68 -> 12.4224 | Q68: =P68 -> 12.4224 | R68: =Q68 -> 12.4224 | S68: =R68 -> 12.4224 | T68: =S68 -> 12.4224 | ... V68: =U68 -> 12.4224
D69: Total Liabilities | F69: ₹ in Cr | H69: =SUM(H61:H68) -> 576.6606 | I69: =SUM(I61:I68) -> 715.0244 | J69: =SUM(J61:J68) -> 892.2566 | K69: =SUM(K61:K68) -> 1227.907 | L69: =SUM(L61:L68) -> 1458.7758 | M69: =SUM(M61:M68) -> 1504.6722 | N69: =SUM(N61:N68) -> 1540.1354 | O69: =SUM(O61:O68) -> 1575.7865 | ... V69: =SUM(V61:V68) -> 1804.5635
C70: Shareholder's Equity
D71: Equity Capital | F71: ₹ in Cr | H71: =Historical!H68 -> 40.418 | I71: =Historical!I68 -> 40.418 | J71: =Historical!J68 -> 40.418 | K71: =Historical!K68 -> 40.418 | L71: =Historical!L68 -> 40.418 | M71: =L71 -> 40.418 | N71: =M71 -> 40.418 | O71: =N71 -> 40.418 | P71: =O71 -> 40.418 | Q71: =P71 -> 40.418 | R71: =Q71 -> 40.418 | S71: =R71 -> 40.418 | T71: =S71 -> 40.418 | ... V71: =U71 -> 40.418
D72: Retained Earnings | F72: ₹ in Cr | H72: =Historical!H69 -> 2128.016 | I72: =Historical!I69 -> 2375.9576 | J72: =Historical!J69 -> 2669.6983 | K72: =Historical!K69 -> 2838.7768 | L72: =Historical!L69 -> 3150.7848 | M72: =L72+M37+M102 -> 3558.1779 | N72: =M72+N37+N102 -> 4024.1636 | O72: =N72+O37+O102 -> 4472.6732 | P72: =O72+P37+P102 -> 4877.8039 | Q72: =P72+Q37+Q102 -> 5305.9617 | R72: =Q72+R37+R102 -> 5772.3665 | S72: =R72+S37+S102 -> 6224.968 | T72: =S72+T37+T102 -> 6765.336 | ... V72: =U72+V37+V102 -> 8120.7765
D73: Total Shareholder's Equity | F73: ₹ in Cr | H73: =SUM(H71:H72) -> 2168.434 | I73: =SUM(I71:I72) -> 2416.3756 | J73: =SUM(J71:J72) -> 2710.1163 | K73: =SUM(K71:K72) -> 2879.1948 | L73: =SUM(L71:L72) -> 3191.2028 | M73: =SUM(M71:M72) -> 3598.5959 | N73: =SUM(N71:N72) -> 4064.5816 | O73: =SUM(O71:O72) -> 4513.0912 | ... V73: =SUM(V71:V72) -> 8161.1945
D74: Non Controlling Interest | F74: ₹ in Cr | H74: =Historical!H70 -> 0 | I74: =Historical!I70 -> 0 | J74: =Historical!J70 -> - | K74: =Historical!K70 -> -0.2527 | L74: =Historical!L70 -> -3.1216 | M74: =L74 -> -3.1216 | N74: =M74 -> -3.1216 | O74: =N74 -> -3.1216 | P74: =O74 -> -3.1216 | Q74: =P74 -> -3.1216 | R74: =Q74 -> -3.1216 | S74: =R74 -> -3.1216 | T74: =S74 -> -3.1216 | ... V74: =U74 -> -3.1216
D75: Total Liabilities & Shahreholder Equity | F75: ₹ in Cr | H75: =SUM(H73:H74,H69) -> 2745.0946 | I75: =SUM(I73:I74,I69) -> 3131.4 | J75: =SUM(J73:J74,J69) -> 3602.3729 | K75: =SUM(K73:K74,K69) -> 4106.8491 | L75: =SUM(L73:L74,L69) -> 4646.857 | M75: =SUM(M73:M74,M69) -> 5100.1465 | N75: =SUM(N73:N74,N69) -> 5601.5954 | O75: =SUM(O73:O74,O69) -> 6085.7561 | ... V75: =SUM(V73:V74,V69) -> 9962.6365
D76: Check | H76: =H75-H57 -> 0 | I76: =I75-I57 -> 0 | J76: =J75-J57 -> 0 | K76: =K75-K57 -> 0 | L76: =L75-L57 -> 0 | M76: =M75-M57 -> 0 | N76: =N75-N57 -> 0 | O76: =O75-O57 -> 0 | ... V76: =V75-V57 -> 0
A77: Cashflow Statement
B79: Cashflow from Operating Acitvities
D80: Profit Before Tax | F80: ₹ in Cr | H80: =Historical!H103 -> 243.6535 | I80: =Historical!I103 -> 379.6675 | J80: =Historical!J103 -> 423.579 | K80: =Historical!K103 -> 225.6741 | L80: =Historical!L103 -> 543.621 | M80: =M35 -> 569.57176 | N80: =N35 -> 655.89486 | O80: =O35 -> 631.2966 | P80: =P35 -> 574.1213 | Q80: =Q35 -> 606.75363 | R80: =R35 -> 665.48524 | S80: =S35 -> 645.79012 | T80: =T35 -> 776.34063 | ... V80: =V35 -> 1023.1431
D81: (+/-) Depriciation&Amortisation | F81: ₹ in Cr | H81: =Historical!H105+Historical!H106 -> 121.6295 | I81: =Historical!I105+Historical!I106 -> 131.1122 | J81: =Historical!J105+Historical!J106 -> 146.5977 | K81: =Historical!K105+Historical!K106 -> 331.9105 | L81: =Historical!L105+Historical!L106 -> 365.2867 | M81: =M11*L51 -> 394.00281 | N81: =N11*M51 -> 423.76073 | O81: =O11*N51 -> 565.05525 | P81: =P11*O51 -> 738.3165 | Q81: =Q11*P51 -> 820.06282 | R81: =R11*Q51 -> 873.05214 | S81: =S11*R51 -> 1001.0146 | T81: =T11*S51 -> 974.63659 | ... V81: =V11*U51 -> 922.06081
D82: (+/-) Finance Costs | F82: ₹ in Cr | H82: =SUM(Historical!H109:H110) -> -19.7835 | I82: =SUM(Historical!I109:I110) -> -33.6529 | J82: =SUM(Historical!J109:J110) -> -6.9207 | K82: =SUM(Historical!K109:K110) -> 28.4197 | L82: =SUM(Historical!L109:L110) -> 34.6377 | M82: =-M129 -> 28.570994 | N82: =-N129 -> 28.570994 | O82: =-O129 -> 28.570994 | P82: =-P129 -> 28.570994 | Q82: =-Q129 -> 28.570994 | R82: =-R129 -> 28.570994 | S82: =-S129 -> 28.570994 | T82: =-T129 -> 28.570994 | ... V82: =-V129 -> 28.570994
D83: (+/-) Non Operating Income/Expenses | F83: ₹ in Cr | H83: =SUM(Historical!H111,Historical!H112,Historical!H108,Historical!H107) -> 0.0963 | I83: =SUM(Historical!I111,Historical!I112,Historical!I108,Historical!I107) -> 7.4643 | J83: =SUM(Historical!J111,Historical!J112,Historical!J108,Historical!J107) -> -1.3507 | K83: =SUM(Historical!K111,Historical!K112,Historical!K108,Historical!K107) -> 1.986 | L83: =SUM(Historical!L111,Historical!L112,Historical!L108,Historical!L107) -> 5.5943 | M83: 0 | N83: 0 | O83: 0 | P83: 0 | Q83: 0 | R83: 0 | S83: 0 | T83: 0 | U83: 0 | V83: 0
D84: (+/-) Change In Working Capital | F84: ₹ in Cr | H84: =SUM(Historical!H115:H119) -> 106.4778 | I84: =SUM(Historical!I115:I119) -> -41.652 | J84: =SUM(Historical!J115:J119) -> 4.0786 | K84: =SUM(Historical!K115:K119) -> -222.5747 | L84: =SUM(Historical!L115:L119) -> -75.2458 | M84: =M117 -> 69.653183 | N84: =N117 -> -44.505995 | O84: =O117 -> -44.741877 | P84: =P117 -> -44.507876 | Q84: =Q117 -> -43.853299 | R84: =R117 -> -42.834311 | S84: =S117 -> -41.510188 | T84: =T117 -> -39.940214 | ... V84: =V117 -> -36.286136
C85: Cash Generated from Operations | F85: ₹ in Cr | H85: =SUM(H80:H84) -> 452.0736 | I85: =SUM(I80:I84) -> 442.9391 | J85: =SUM(J80:J84) -> 565.9839 | K85: =SUM(K80:K84) -> 365.4156 | L85: =SUM(L80:L84) -> 873.8939 | M85: =SUM(M80:M84) -> 1061.7987 | N85: =SUM(N80:N84) -> 1063.7206 | O85: =SUM(O80:O84) -> 1180.181 | ... V85: =SUM(V80:V84) -> 1937.4888
D86: Income Tax Paid | H86: =Historical!H121 -> -35 | I86: =Historical!I121 -> -67.7102 | J86: =Historical!J121 -> -76.2373 | K86: =Historical!K121 -> -68.9442 | L86: =Historical!L121 -> -109.0368 | M86: =M36 -> -145.58517 | N86: =N36 -> -170.92922 | O86: =O36 -> -164.5188 | P86: =P36 -> -152.48926 | Q86: =Q36 -> -161.15656 | R86: =R36 -> -180.08337 | S86: =S36 -> -174.75378 | T86: =T36 -> -213.96306 | ... V86: =V36 -> -287.09868
D87: Net Cashflow from Operating Activities | H87: =SUM(H85:H86) -> 417.0736 | I87: =SUM(I85:I86) -> 375.2289 | J87: =SUM(J85:J86) -> 489.7466 | K87: =SUM(K85:K86) -> 296.4714 | L87: =SUM(L85:L86) -> 764.8571 | M87: =SUM(M85:M86) -> 916.21358 | N87: =SUM(N85:N86) -> 892.79137 | O87: =SUM(O85:O86) -> 1015.6622 | ... V87: =SUM(V85:V86) -> 1650.3901
C90: Cashflow from Investing Activities
D91: (-) Investments in Properties and equipment | F91: ₹ in Cr | H91: =Historical!H124 -> -199.4384 | I91: =Historical!I124 -> -571.8581 | J91: =Historical!J124 -> -1036.4551 | K91: =Historical!K124 -> -581.1857 | L91: =Historical!L124 -> -493.1995 | M91: =-M121 -> -589.56522 | N91: =-N121 -> -1352.3165 | O91: =-O121 -> -1140.041 | P91: =-P121 -> -1213.1279 | Q91: =-Q121 -> -1127.8434 | R91: =-R121 -> -1011.1754 | S91: =-S121 -> -863.74775 | T91: =-T121 -> -686.65668 | ... V91: =-V121 -> -249.62536
D92: (+) Sale of Property plant and Equipment | F92: ₹ in Cr | H92: =Historical!H125 -> 2.0823 | I92: =Historical!I125 -> 2.414 | J92: =Historical!J125 -> 0.3796 | K92: =Historical!K125 -> 5.5181 | L92: =Historical!L125 -> 6.4844 | M92: 0 | N92: 0 | O92: 0 | P92: 0 | Q92: 0 | R92: 0 | S92: 0 | T92: 0 | U92: 0 | V92: 0
D93: (+) Investment Made in Instruments | F93: ₹ in Cr | H93: =Historical!H126+Historical!H127 -> 39.6425 | I93: =Historical!I126+Historical!I127 -> 186.4711 | J93: =Historical!J126+Historical!J127 -> 181.2856 | K93: =Historical!K126+Historical!K127 -> 39.781 | L93: =Historical!L126+Historical!L127 -> -100.9082 | M93: 0 | N93: 0 | O93: 0 | P93: 0 | Q93: 0 | R93: 0 | S93: 0 | T93: 0 | U93: 0 | V93: 0
D94: (-) Sale of investments | F94: ₹ in Cr | H94: =Historical!H128-Historical!H126 -> -161.9 | I94: =Historical!I128-Historical!I126 -> 64.6882 | J94: =Historical!J128-Historical!J126 -> 173.4977 | K94: =Historical!K128-Historical!K126 -> -4.5425 | L94: =Historical!L128-Historical!L126 -> -254.7258 | M94: 0 | N94: 0 | O94: 0 | P94: 0 | Q94: 0 | R94: 0 | S94: 0 | T94: 0 | U94: 0 | V94: 0
D95: (+) Interest and Dividend received | F95: ₹ in Cr | H95: =Historical!H129+Historical!H126 -> 30.7674 | I95: =Historical!I129+Historical!I126 -> 46.5993 | J95: =Historical!J129+Historical!J126 -> 31.2299 | K95: =Historical!K129+Historical!K126 -> 11.8799 | L95: =Historical!L129+Historical!L126 -> -0.9742 | M95: 0 | N95: 0 | O95: 0 | P95: 0 | Q95: 0 | R95: 0 | S95: 0 | T95: 0 | U95: 0 | V95: 0
D96: Cash From Investing Activity | F96: ₹ in Cr | H96: =SUM(H91:H95) -> -288.8462 | I96: =SUM(I91:I95) -> -271.6855 | J96: =SUM(J91:J95) -> -650.0623 | K96: =SUM(K91:K95) -> -528.5492 | L96: =SUM(L91:L95) -> -843.3233 | M96: =SUM(M91:M95) -> -589.56522 | N96: =SUM(N91:N95) -> -1352.3165 | O96: =SUM(O91:O95) -> -1140.041 | ... V96: =SUM(V91:V95) -> -249.62536
C98: Cashflow from Financing Activities
D99: Buy back of Equity Shares | H99: =Historical!H132 -> -152.3604 | I99: =Historical!I132 -> 0 | J99: =Historical!J132 -> 72.1026 | K99: =Historical!K132 -> 241.9331 | L99: =Historical!L132 -> 288.0007 | M99: 0 | N99: 0 | O99: 0 | P99: 0 | Q99: 0 | R99: 0 | S99: 0 | T99: 0 | U99: 0 | V99: 0
D100: Repayment of Long Term Borrowings | F100: ₹ in Cr | H100: =Historical!H136+Historical!H133 -> -0.661 | I100: =Historical!I136+Historical!I133 -> -1.0275 | J100: =Historical!J136+Historical!J133 -> -6.5308 | K100: =Historical!K136+Historical!K133 -> -5.8907 | L100: =Historical!L136+Historical!L133 -> -48.126 | M100: 0 | N100: 0 | O100: 0 | P100: 0 | Q100: 0 | R100: 0 | S100: 0 | T100: 0 | U100: 0 | V100: 0
D101: Proceeds from share allotment | F101: ₹ in Cr | H101: =Historical!H134+Historical!H142+Historical!H144+Historical!H143 -> -9.7468 | I101: =Historical!I134+Historical!I142+Historical!I144+Historical!I143 -> 20.7257 | J101: =Historical!J134+Historical!J142+Historical!J144+Historical!J143 -> 31.6229 | K101: =Historical!K134+Historical!K142+Historical!K144+Historical!K143 -> 16.9164 | L101: =Historical!L134+Historical!L142+Historical!L144+Historical!L143 -> -59.3597 | M101: 0 | N101: 0 | O101: 0 | P101: 0 | Q101: 0 | R101: 0 | S101: 0 | T101: 0 | U101: 0 | V101: 0
D102: Dividend Paid | F102: ₹ in Cr | H102: =Historical!H137 -> 0 | I102: =Historical!I137 -> 0 | J102: =Historical!J137 -> 0 | K102: =Historical!K137 -> 0 | L102: =Historical!L137 -> -80.8361 | M102: =-M37*M14 -> -16.59347 | N102: =-N37*N14 -> -18.979994 | O102: =-O37*O14 -> -18.26818 | P102: =-P37*P14 -> -16.50132 | Q102: =-Q37*Q14 -> -17.439235 | R102: =-R37*R14 -> -18.997066 | S102: =-S37*S14 -> -18.434846 | T102: =-T37*T14 -> -22.009648 | ... V102: =-V37*V14 -> -28.806411
D103: Interest Paid | F103: ₹ in Cr | H103: =Historical!H135 -> -12.8667 | I103: =Historical!I135 -> -9.695 | J103: =Historical!J135 -> -10.7144 | K103: =Historical!K135 -> -28.8216 | L103: =Historical!L135 -> -47.9227 | M103: =M129 -> -28.570994 | N103: =N129 -> -28.570994 | O103: =O129 -> -28.570994 | P103: =P129 -> -28.570994 | Q103: =Q129 -> -28.570994 | R103: =R129 -> -28.570994 | S103: =S129 -> -28.570994 | T103: =T129 -> -28.570994 | ... V103: =V129 -> -28.570994
D104: Cash From Financing Activities | F104: ₹ in Cr | H104: =SUM(H99:H103) -> -175.6349 | I104: =SUM(I99:I103) -> 10.0032 | J104: =SUM(J99:J103) -> 86.4803 | K104: =SUM(K99:K103) -> 224.1372 | L104: =SUM(L99:L103) -> 51.7562 | M104: =SUM(M100:M103) -> -45.164464 | N104: =SUM(N100:N103) -> -47.550988 | O104: =SUM(O100:O103) -> -46.839175 | P104: =SUM(P100:P103) -> -45.072315 | Q104: =SUM(Q100:Q103) -> -46.010229 | R104: =SUM(R100:R103) -> -47.568061 | S104: =SUM(S100:S103) -> -47.00584 | T104: =SUM(T100:T103) -> -50.580642 | ... V104: =SUM(V100:V103) -> -57.377405
B105: Net Cashflow | F105: ₹ in Cr | H105: =H104+H96+H87 -> -47.4075 | I105: =I104+I96+I87 -> 113.5466 | J105: =J104+J96+J87 -> -73.8354 | K105: =K104+K96+K87 -> -7.9406 | L105: =L104+L96+L87 -> -26.71 | M105: =M104+M96+M87 -> 281.48389 | N105: =N104+N96+N87 -> -507.07616 | O105: =O104+O96+O87 -> -171.21797 | ... V105: =V104+V96+V87 -> 1343.3874
D106: Opening Cash Balance | F106: ₹ in Cr | H106: =Historical!H140 -> 55.483 | I106: =Historical!I140 -> 8.0755 | J106: =Historical!J140 -> 121.6223 | K106: =Historical!K140 -> 47.7869 | L106: =Historical!L140 -> 39.8463 | M106: =L43 -> 13.1363 | N106: =M43 -> 294.62019 | O106: =N43 -> -212.45596 | P106: =O43 -> -383.67394 | Q106: =P43 -> -497.86249 | R106: =Q43 -> -421.33853 | S106: =R43 -> -135.89133 | T106: =S43 -> 412.46682 | ... V106: =U43 -> 2248.8232
D107: Closing Cash Balance | F107: ₹ in Cr | H107: =SUM(H105:H106) -> 8.0755 | I107: =SUM(I105:I106) -> 121.6221 | J107: =SUM(J105:J106) -> 47.7869 | K107: =SUM(K105:K106) -> 39.8463 | L107: =SUM(L105:L106) -> 13.1363 | M107: =SUM(M105:M106) -> 294.62019 | N107: =SUM(N105:N106) -> -212.45596 | O107: =SUM(O105:O106) -> -383.67394 | ... V107: =SUM(V105:V106) -> 3592.2105
A109: Supporting Schedules
C111: Working Capital
D112: Net Working Capital | F112: ₹ in Cr | H112: =H45+H49+H47-H61-H63+H46-H62 -> 47.7023 | I112: =I45+I49+I47-I61-I63+I46-I62 -> 116.1342 | J112: =J45+J49+J47-J61-J63+J46-J62 -> -123.5547 | K112: =K45+K49+K47-K61-K63+K46-K62 -> -88.7807 | L112: =L45+L49+L47-L61-L63+L46-L62 -> -31.0267 | M112: =M45+M49+M47-M61-M63+M46-M62 -> -100.67988 | N112: =N45+N49+N47-N61-N63+N46-N62 -> -56.173888 | O112: =O45+O49+O47-O61-O63+O46-O62 -> -11.432011 | ... V112: =V45+V49+V47-V61-V63+V46-V62 -> 275.68129
...

Sheet Ratio Analysis
A1: Star Cements | G1: Historical Period | L1: Forcasted Period | X1: Interpretation of ratios
A2: Ratio Analysis | G2: 2022 | H2: =G2+1 -> 2023 | I2: =H2+1 -> 2024 | J2: =I2+1 -> 2025 | K2: =J2+1 -> 2026 | L2: 2027 | M2: =L2+1 -> 2028 | N2: =M2+1 -> 2029 | O2: =N2+1 -> 2030 | P2: =O2+1 -> 2031 | Q2: =P2+1 -> 2032 | R2: =Q2+1 -> 2033 | S2: =R2+1 -> 2034 | T2: =S2+1 -> 2035 | U2: =T2+1 -> 2036 | V2: Trend
D4: Particulars
D5: Profitability Ratios
D6: Gross Margin | G6: =Model!H25/Model!H23 -> 0.75814289 | H6: =Model!I25/Model!I23 -> 0.76655566 | I6: =Model!J25/Model!J23 -> 0.84238752 | J6: =Model!K25/Model!K23 -> 0.82161084 | K6: =Model!L25/Model!L23 -> 0.86931602 | L6: =Model!M25/Model!M23 -> 0.84443812 | M6: =Model!N25/Model!N23 -> 0.84443812 | N6: =Model!O25/Model!O23 -> 0.84443812 | ... U6: =Model!V25/Model!V23 -> 0.84443812 | X6: Star Cement's gross margin has strengthened materially, and the forecast assumes it remains stable at ~84%, providing a strong gross-profit base while avoiding reliance on the unusually high FY2026 margin.
D7: EBITDA Margin | G7: =Model!H29/Model!H23 -> 0.1678897 | H7: =Model!I29/Model!I23 -> 0.18878782 | I7: =Model!J29/Model!J23 -> 0.19841732 | J7: =Model!K29/Model!K23 -> 0.18563796 | K7: =Model!L29/Model!L23 -> 0.25165321 | L7: =Model!M29/Model!M23 -> 0.23131274 | M7: =Model!N29/Model!N23 -> 0.23131274 | N7: =Model!O29/Model!O23 -> 0.23131274 | ... U7: =Model!V29/Model!V23 -> 0.23131274 | X7: EBITDA Margin improved from 16.79% in FY2022 to 25.17% in FY2026, the best year in the historical set. My forecast normalises this to a stable 23.13% from FY2028 onwards, since Salaries and Other SG&A are both held at their five-year historical average as a percentage of revenue.
D8: Operating Margin | G8: =Model!H31/Model!H23 -> 0.11395657 | H8: =Model!I31/Model!I23 -> 0.14123049 | I8: =Model!J31/Model!J23 -> 0.14850547 | J8: =Model!K31/Model!K23 -> 0.081065009 | K8: =Model!L31/Model!L23 -> 0.15541745 | L8: =Model!M31/Model!M23 -> 0.13945337 | M8: =Model!N31/Model!N23 -> 0.14286399 | N8: =Model!O31/Model!O23 -> 0.12460849 | ... U8: =Model!V31/Model!V23 -> 0.12325361 | X8: Operating Margin swung between 8.11% (FY2025) and 15.54% (FY2026) historically, and stays volatile in the forecast too — it dips to around 10.7%–11.2% between FY2030–FY2032 before recovering to 12.33% by FY2036. This isn't a change in operating assumptions; it's the depreciation schedule, since D&A steps up +2.00% of opening PP&E every three years as the FY2028 capex (28.23% of revenue) starts amortising.
D9: Pretax Margin | G9: =Model!H35/Model!H23 -> 0.1080412 | H9: =Model!I35/Model!I23 -> 0.1377139 | I9: =Model!J35/Model!J23 -> 0.14421516 | J9: =Model!K35/Model!K23 -> 0.071101718 | K9: =Model!L35/Model!L23 -> 0.14620061 | L9: =Model!M35/Model!M23 -> 0.13279221 | M9: =Model!N35/Model!N23 -> 0.13690056 | N9: =Model!O35/Model!O23 -> 0.11921318 | ... U9: =Model!V35/Model!V23 -> 0.11990528 | X9: Pretax margin improved from 10.80% in FY2022 to 14.62% in FY2026, but the forecast shows a gradual decline, reaching 9.70% in FY2033, before recovering to 11.99% by FY2036
D10: Effective Tax rate | G10: =Model!H13 -> -0.012810405 | H10: =Model!I13 -> 0.34783962 | I10: =Model!J13 -> 0.30329336 | J10: =Model!K13 -> 0.25191859 | K10: =Model!L13 -> 0.25560461 | L10: =Model!M13 -> 0.25560461 | M10: =Model!N13 -> 0.26060461 | N10: =Model!O13 -> 0.26060461 | ... U10: =Model!V13 -> 0.28060461 | X10: The effective tax rate swung from a -1.28% credit in FY2022 to 34.78% in FY2023, before settling at 25.56% in FY2026. Rather than carrying FY2026's rate forward indefinitely, I step it up by 0.50% every two years to reach 28.06% by FY2036, avoiding reliance on a single year's favourable tax outcome.
D11: Net Margin | G11: =Model!H37/Model!H23 -> 0.10942525 | H11: =Model!I37/Model!I23 -> 0.089811546 | I11: =Model!J37/Model!J23 -> 0.10047566 | J11: =Model!K37/Model!K23 -> 0.053189873 | K11: =Model!L37/Model!L23 -> 0.10883106 | L11: =Model!M37/Model!M23 -> 0.098849911 | M11: =Model!N37/Model!N23 -> 0.10122364 | N11: =Model!O37/Model!O23 -> 0.088145676 | ... U11: =Model!V37/Model!V23 -> 0.086259308 | X11: Net margin improved to 10.88% in FY2026 but is forecast to moderate to ~7–10% before gradually recovering to 8.63% by FY2036, indicating stable but limited expansion in bottom-line profitability.
D13: DuPont/Earning Power
D14: Asset Turnover | H14: =Model!I23/AVERAGE(Model!H57:I57) -> 0.93829049 | I14: =Model!J23/AVERAGE(Model!I57:J57) -> 0.87235856 | J14: =Model!K23/AVERAGE(Model!J57:K57) -> 0.82341935 | K14: =Model!L23/AVERAGE(Model!K57:L57) -> 0.86723227 | L14: =Model!M23/AVERAGE(Model!L57:M57) -> 0.88010545 | M14: =Model!N23/AVERAGE(Model!M57:N57) -> 0.89537411 | N14: =Model!O23/AVERAGE(Model!N57:O57) -> 0.90619794 | O14: =Model!P23/AVERAGE(Model!O57:P57) -> 0.91933628 | ... U14: =Model!V23/AVERAGE(Model!U57:V57) -> 0.88935056 | X14: Asset turnover remained broadly stable historically and is expected to improve toward 1.0x before moderating to 0.95x by FY2036, as the expanding asset base broadly keeps pace with revenue growth.
D15: Pre tax ROA | H15: =Model!I35/AVERAGE(Model!H57:I57) -> 0.12921564 | I15: =Model!J35/AVERAGE(Model!I57:J57) -> 0.12580733 | J15: =Model!K35/AVERAGE(Model!J57:K57) -> 0.05854653 | K15: =Model!L35/AVERAGE(Model!K57:L57) -> 0.12678989 | L15: =Model!M35/AVERAGE(Model!L57:M57) -> 0.11687115 | M15: =Model!N35/AVERAGE(Model!M57:N57) -> 0.12257722 | N15: =Model!O35/AVERAGE(Model!N57:O57) -> 0.10803074 | O15: =Model!P35/AVERAGE(Model!O57:P57) -> 0.091042879 | ... U15: =Model!V35/AVERAGE(Model!U57:V57) -> 0.10663783 | X15: Pretax ROA strengthened to ~13% in FY2026 but gradually moderates as the expanding asset base outpaces pretax earnings, indicating slightly lower efficiency in generating pretax returns from assets over the forecast period.
D16: Pre Tax ROE | H16: =Model!I35/AVERAGE(Model!H73:I73) -> 0.16561975 | I16: =Model!J35/AVERAGE(Model!I73:J73) -> 0.16525102 | J16: =Model!K35/AVERAGE(Model!J73:K73) -> 0.080752027 | K16: =Model!L35/AVERAGE(Model!K73:L73) -> 0.18283504 | L16: =Model!M35/AVERAGE(Model!L73:M73) -> 0.1677728 | M16: =Model!N35/AVERAGE(Model!M73:N73) -> 0.17118091 | N16: =Model!O35/AVERAGE(Model!N73:O73) -> 0.14719531 | O16: =Model!P35/AVERAGE(Model!O73:P73) -> 0.1217479 | ... U16: =Model!V35/AVERAGE(Model!U73:V73) -> 0.13104493 | X16: Pre-tax ROE improves to 18% by FY2026 but gradually declines to 13% by FY2036 as shareholders' equity grows faster than pre-tax earnings, indicating moderate deterioration in capital efficiency.
D17: Tax Complement | G17: =Model!H37/Model!H35 -> 1.0128104 | H17: =Model!I37/Model!I35 -> 0.65216038 | I17: =Model!J37/Model!J35 -> 0.69670664 | J17: =Model!K37/Model!K35 -> 0.74808141 | K17: =Model!L37/Model!L35 -> 0.74439539 | L17: =Model!M37/Model!M35 -> 0.74439539 | M17: =Model!N37/Model!N35 -> 0.73939539 | N17: =Model!O37/Model!O35 -> 0.73939539 | ... U17: =Model!V37/Model!V35 -> 0.71939539 | X17: Tax complement declines from 74.44% to 71.94% as the effective tax rate rises, meaning Star Cement retains a slightly smaller share of its pre-tax earnings over time.
D18: ROE | H18: =Model!I37/AVERAGE(Model!H73:I73) -> 0.10801064 | I18: =Model!J37/AVERAGE(Model!I73:J73) -> 0.11513148 | J18: =Model!K37/AVERAGE(Model!J73:K73) -> 0.06040909 | K18: =Model!L37/AVERAGE(Model!K73:L73) -> 0.13610156 | L18: =Model!M37/AVERAGE(Model!L73:M73) -> 0.1248893 | M18: =Model!N37/AVERAGE(Model!M73:N73) -> 0.12657038 | N18: =Model!O37/AVERAGE(Model!N73:O73) -> 0.10883553 | O18: =Model!P37/AVERAGE(Model!O73:P73) -> 0.089411099 | ... U18: =Model!V37/AVERAGE(Model!U73:V73) -> 0.094273115 | X18: Recovers from a low of 6% in FY2025 to a peak of 14% in FY2026, stays elevated near 12-13% through FY2028, then gradually moderates to ~9% by FY2036 as equity compounds faster than net income.
D19: Equity Retention | G19: =(Model!H37+Model!H102)/Model!H37 -> 1 | H19: =(Model!I37+Model!I102)/Model!I37 -> 1 | I19: =(Model!J37+Model!J102)/Model!J37 -> 1 | J19: =(Model!K37+Model!K102)/Model!K37 -> 1 | K19: =(Model!L37+Model!L102)/Model!L37 -> 0.8043161 | L19: =(Model!M37+Model!M102)/Model!M37 -> 0.96086322 | M19: =(Model!N37+Model!N102)/Model!N37 -> 0.96086322 | N19: =(Model!O37+Model!O102)/Model!O37 -> 0.96086322 | ... U19: =(Model!V37+Model!V102)/Model!V37 -> 0.96086322 | X19: Star Cement paid no dividend from FY2022–FY2025, so retention was 100% in those years; FY2026 saw the first payout, taking retention down to 80.43%. My forecast holds the payout ratio at 3.91% (the FY2022–FY2026 average, pulled down by the four zero-dividend years), so retention settles at a high, stable 96.09% from FY2027 onwards.
D20: Reinvestment Rate | H20: =(Model!I37+Model!I102)/AVERAGE(Model!H73:I73) -> 0.10801064 | I20: =(Model!J37+Model!J102)/AVERAGE(Model!I73:J73) -> 0.11513148 | J20: =(Model!K37+Model!K102)/AVERAGE(Model!J73:K73) -> 0.06040909 | K20: =(Model!L37+Model!L102)/AVERAGE(Model!K73:L73) -> 0.10946868 | L20: =(Model!M37+Model!M102)/AVERAGE(Model!L73:M73) -> 0.12000153 | M20: =(Model!N37+Model!N102)/AVERAGE(Model!M73:N73) -> 0.12161682 | N20: =(Model!O37+Model!O102)/AVERAGE(Model!N73:O73) -> 0.10457606 | O20: =(Model!P37+Model!P102)/AVERAGE(Model!O73:P73) -> 0.085911836 | ... U20: =(Model!V37+Model!V102)/AVERAGE(Model!U73:V73) -> 0.090583569 | X20: The reinvestment rate is 12% in FY2026 and is expected to gradually decline to around 9% by FY2036. The FY2027 spike should be treated cautiously because of the EBT formula issue.
D22: Liquidity Ratio
D23: Quick ratio | G23: =(SUM(Model!H43:H49)-Model!H47)/SUM(Model!H61:H63) -> 1.9261004 | H23: =(SUM(Model!I43:I49)-Model!I47)/SUM(Model!I61:I63) -> 1.1794141 | I23: =(SUM(Model!J43:J49)-Model!J47)/SUM(Model!J61:J63) -> 0.55222835 | J23: =(SUM(Model!K43:K49)-Model!K47)/SUM(Model!K61:K63) -> 0.65647315 | K23: =(SUM(Model!L43:L49)-Model!L47)/SUM(Model!L61:L63) -> 0.80023491 | L23: =(SUM(Model!M43:M49)-Model!M47)/SUM(Model!M61:M63) -> 1.0246168 | M23: =(SUM(Model!N43:N49)-Model!N47)/SUM(Model!N61:N63) -> 0.50666856 | N23: =(SUM(Model!O43:O49)-Model!O47)/SUM(Model!O61:O63) -> 0.34829565 | ... U23: =(SUM(Model!V43:V49)-Model!V47)/SUM(Model!V61:V63) -> 3.5547939 | X23: The Quick Ratio fell from 1.93x in FY2022 to 0.55x in FY2024, indicating weaker short-term liquidity, before recovering to 0.80x in FY2026. The forecast rises sharply to 3.61x by FY2036.
D24: Current ratio | G24: =SUM(Model!H43:H49)/SUM(Model!H61:H63) -> 2.4151301 | H24: =SUM(Model!I43:I49)/SUM(Model!I61:I63) -> 1.8872949 | I24: =SUM(Model!J43:J49)/SUM(Model!J61:J63) -> 0.98167253 | J24: =SUM(Model!K43:K49)/SUM(Model!K61:K63) -> 1.1545459 | K24: =SUM(Model!L43:L49)/SUM(Model!L61:L63) -> 1.306564 | L24: =SUM(Model!M43:M49)/SUM(Model!M61:M63) -> 1.5113982 | M24: =SUM(Model!N43:N49)/SUM(Model!N61:N63) -> 1.0311387 | N24: =SUM(Model!O43:O49)/SUM(Model!O61:O63) -> 0.90805498 | ... U24: =SUM(Model!V43:V49)/SUM(Model!V61:V63) -> 4.2936844 | X24: Current ratio declined from 2.42x in FY2022 to 1.31x in FY2026, showing that the company's short-term liquidity cushion narrowed. It then rises sharply in the forecast, reaching 4.41x by FY2036, primarily due to accumulating cash.
D25: Cash Cycle (Days) | G25: =Model!H15+Model!H16-Model!H17 -> 0 | H25: =Model!I15+Model!I16-Model!I17 -> 36.695178 | I25: =Model!J15+Model!J16-Model!J17 -> 98.019409 | J25: =Model!K15+Model!K16-Model!K17 -> 126.54672 | K25: =Model!L15+Model!L16-Model!L17 -> 176.54835 | L25: =Model!M15+Model!M16-Model!M17 -> 109.45241 | M25: =Model!N15+Model!N16-Model!N17 -> 109.45241 | N25: =Model!O15+Model!O16-Model!O17 -> 109.45241 | ... U25: =Model!V15+Model!V16-Model!V17 -> 109.45241 | X25: The normalised 109.45-day cash cycle assumes working-capital requirements stabilise, reducing the extreme FY2026 working-capital burden while remaining structurally positive.
D27: Leverage
D28: Asset/Equity | G28: =Model!H57/Model!H73 -> 1.2659341 | H28: =Model!I57/Model!I73 -> 1.2959078 | I28: =Model!J57/Model!J73 -> 1.3292318 | J28: =Model!K57/Model!K73 -> 1.4263881 | K28: =Model!L57/Model!L73 -> 1.4561459 | L28: =Model!M57/Model!M73 -> 1.4172601 | M28: =Model!N57/Model!N73 -> 1.3781481 | N28: =Model!O57/Model!O73 -> 1.3484673 | ... U28: =Model!V57/Model!V73 -> 1.2207326 | X28: The Asset/Equity multiplier increased from 1.27x in FY2022 to 1.46x in FY2026, indicating greater use of liabilities to support the asset base. It then declines gradually to 1.22x by FY2036 as retained earnings increase shareholders' equity.
D29: Debt/Equity | G29: =Model!H65/Model!H73 -> 0.0036930799 | H29: =Model!I65/Model!I73 -> 0.0020023377 | I29: =Model!J65/Model!J73 -> 0.026604984 | J29: =Model!K65/Model!K73 -> 0.10167044 | K29: =Model!L65/Model!L73 -> 0.15454552 | L29: =Model!M65/Model!M73 -> 0.13704959 | M29: =Model!N65/Model!N73 -> 0.12133748 | N29: =Model!O65/Model!O73 -> 0.109279 | ... U29: =Model!V65/Model!V73 -> 0.060430627 | X29: Debt/Equity increased from 0.03x in FY2024 to 0.15x in FY2026, reflecting increased borrowing to support capacity expansion. It then falls steadily to 0.06x by FY2036, as debt remains at approximately ₹493 Cr while equity continues to grow through retained earnings.
D30: % LT Debt to Total Capital | G30: =Model!H65/SUM(Model!H65+Model!H73) -> 0.0036794912 | H30: =Model!I65/SUM(Model!I65+Model!I73) -> 0.0019983364 | I30: =Model!J65/SUM(Model!J65+Model!J73) -> 0.025915502 | J30: =Model!K65/SUM(Model!K65+Model!K73) -> 0.092287526 | K30: =Model!L65/SUM(Model!L65+Model!L73) -> 0.13385832 | L30: =Model!M65/SUM(Model!M65+Model!M73) -> 0.12053088 | M30: =Model!N65/SUM(Model!N65+Model!N73) -> 0.10820782 | N30: =Model!O65/SUM(Model!O65+Model!O73) -> 0.09851354 | ... U30: =Model!V65/SUM(Model!V65+Model!V73) -> 0.056986874 | X30: Long-term debt represented 13.39% of total capital in FY2026, up from 0% in FY2022, reflecting the company's increased reliance on debt during its expansion. The ratio declines to ~6% by FY2036 as the equity base expands while debt remains broadly unchanged.
D31: Debt/ebitda | G31: =(Model!H65/Model!H29) -> 0.021150838 | H31: =(Model!I65/Model!I29) -> 0.0092961291 | I31: =(Model!J65/Model!J29) -> 0.12372226 | J31: =(Model!K65/Model!K29) -> 0.49681802 | K31: =(Model!L65/Model!L29) -> 0.51631051 | L31: =(Model!M65/Model!M29) -> 0.49709047 | M31: =(Model!N65/Model!N29) -> 0.4450228 | N31: =(Model!O65/Model!O29) -> 0.40262626 | ... U31: =(Model!V65/Model!V29) -> 0.24986947 | X31: Debt/EBITDA increased sharply from 0.02x in FY2022 to 0.52x in FY2026, reflecting debt-funded expansion. It subsequently declines to 0.25x by FY2036 as EBITDA grows while debt is held at approximately ₹493 Cr.
D32: Operating
D33: A/R Turnover | H33: =365/Model!I15 -> 23.619996 | I33: =365/Model!J15 -> 22.99404 | J33: =365/Model!K15 -> 18.120417 | K33: =365/Model!L15 -> 17.206876 | L33: =365/Model!M15 -> 20.08746 | M33: =365/Model!N15 -> 20.08746 | N33: =365/Model!O15 -> 20.08746 | O33: =365/Model!P15 -> 20.08746 | ... U33: =365/Model!V15 -> 20.08746 | X33: A/R turnover stabilises at 20.09x from FY2027, reflecting an assumption of broadly unchanged dealer credit and collection efficiency.
D34: Avg. A/R Days | H34: =Model!I15 -> 15.453008 | I34: =Model!J15 -> 15.873679 | J34: =Model!K15 -> 20.143025 | K34: =Model!L15 -> 21.21245 | L34: =Model!M15 -> 18.170541 | M34: =Model!N15 -> 18.170541 | N34: =Model!O15 -> 18.170541 | O34: =Model!P15 -> 18.170541 | ... U34: =Model!V15 -> 18.170541 | X34: Receivable days increased from 15.45 days in FY2022 to 21.21 days in FY2026, I have maintained 18.17 days average throughout the forecast, based on the FY2023–FY2026 average, as I have not assumed any material change in Star Cement's collection cycle.
D35: Inventory Turnover | H35: =365/Model!I16 -> 2.2605617 | I35: =365/Model!J16 -> 1.3057254 | J35: =365/Model!K16 -> 1.4493483 | K35: =365/Model!L16 -> 1.087864 | L35: =365/Model!M16 -> 1.4197368 | M35: =365/Model!N16 -> 1.4197368 | N35: =365/Model!O16 -> 1.4197368 | O35: =365/Model!P16 -> 1.4197368 | ... U35: =365/Model!V16 -> 1.4197368 | X35: Inventory Turnover is low throughout — around 1.1x–1.4x — because a cement manufacturer holds large limestone, coal and clinker stockpiles; it settles at 1.42x from FY2027 onward, the mechanical inverse of the 257.09-day DIO assumption.
D36: Avg. Inventory Days | H36: =Model!I16 -> 161.46429 | I36: =Model!J16 -> 279.53809 | J36: =Model!K16 -> 251.83733 | K36: =Model!L16 -> 335.51989 | L36: =Model!M16 -> 257.0899 | M36: =Model!N16 -> 257.0899 | N36: =Model!O16 -> 257.0899 | O36: =Model!P16 -> 257.0899 | ... U36: =Model!V16 -> 257.0899 | X36: Inventory days increased from 161.46 days in FY2023 to 335.52 days in FY2026, showing a significant increase in inventory held by Star Cement. From FY2027 onward, I have normalised inventory days to 257.09 days, based on the FY2023–FY2026 average.
D37: A/P Turnover | H37: =365/Model!I17 -> 2.6030129 | I37: =365/Model!J17 -> 1.849109 | J37: =365/Model!K17 -> 2.5097359 | K37: =365/Model!L17 -> 2.0257071 | L37: =365/Model!M17 -> 2.2013409 | M37: =365/Model!N17 -> 2.2013409 | N37: =365/Model!O17 -> 2.2013409 | O37: =365/Model!P17 -> 2.2013409 | ... U37: =365/Model!V17 -> 2.2013409 | X37: A/P Turnover stabilises at 2.20x from FY2027 onwards, the mechanical inverse of the 165.81-day DPO carried forward from the FY2023–FY2026 average.
D38: Avg. A/P Days | H38: =Model!I17 -> 140.22213 | I38: =Model!J17 -> 197.39236 | J38: =Model!K17 -> 145.43363 | K38: =Model!L17 -> 180.184 | L38: =Model!M17 -> 165.80803 | M38: =Model!N17 -> 165.80803 | N38: =Model!O17 -> 165.80803 | O38: =Model!P17 -> 165.80803 | ... U38: =Model!V17 -> 165.80803 | X38: Payable days are held flat at 165.81 days throughout the forecast, in line with the FY2023–FY2026 average — I haven't assumed any change in supplier credit terms.
D39: Fixed Asset Turnover | H39: =Model!I23/AVERAGE(Model!H51:I51) -> 3.0949771 | I39: =Model!J23/AVERAGE(Model!I51:J51) -> 2.5881507 | J39: =Model!K23/AVERAGE(Model!J51:K51) -> 1.6718263 | K39: =Model!L23/AVERAGE(Model!K51:L51) -> 1.5213786 | L39: =Model!M23/AVERAGE(Model!L51:M51) -> 1.5962297 | M39: =Model!N23/AVERAGE(Model!M51:N51) -> 1.4745545 | N39: =Model!O23/AVERAGE(Model!N51:O51) -> 1.323581 | O39: =Model!P23/AVERAGE(Model!O51:P51) -> 1.2809612 | ... U39: =Model!V23/AVERAGE(Model!U51:V51) -> 2.1280581 | X39: Fixed asset turnover falls as Star Cement's expansion increases the asset base faster than revenue, before recovering to 2.13x by FY2036 as the new assets are increasingly utilised and revenue compounds.
D40: ROIC | G40: =(Model!H31+Model!H36)/(Model!H65+Model!H73-Model!H43) -> 0.119959 | H40: =(Model!I31+Model!I36)/(Model!I65+Model!I73-Model!I43) -> 0.11188904 | I40: =(Model!J31+Model!J36)/(Model!J65+Model!J73-Model!J43) -> 0.11253215 | J40: =(Model!K31+Model!K36)/(Model!K65+Model!K73-Model!K43) -> 0.063997682 | K40: =(Model!L31+Model!L36)/(Model!L65+Model!L73-Model!L43) -> 0.12205101 | L40: =(Model!M31+Model!M36)/(Model!M65+Model!M73-Model!M43) -> 0.11918312 | M40: =(Model!N31+Model!N36)/(Model!N65+Model!N73-Model!N43) -> 0.10765462 | N40: =(Model!O31+Model!O36)/(Model!O65+Model!O73-Model!O43) -> 0.091902278 | ... U40: =(Model!V31+Model!V36)/(Model!V65+Model!V73-Model!V43) -> 0.151045 | X40: ROIC temporarily declines as Star Cement's expansion increases invested capital faster than operating profits, but recovers to 15.00% by FY2036 as the new capacity contributes to earnings and capital utilisation improves.

Sheet Scenario Analysis
A1: Star Cements
A2: Scenarios
C4: Scenarios | E4: Growth | H4: 2027 | I4: =H4+1 -> 2028 | J4: =I4+1 -> 2029 | K4: =J4+1 -> 2030 | L4: =K4+1 -> 2031 | M4: =L4+1 -> 2032 | N4: =M4+1 -> 2033 | O4: =N4+1 -> 2034 | P4: =O4+1 -> 2035 | Q4: =P4+1 -> 2036
D5: Base Case | E5: 0.13 | H5: {=E5:E7} -> 0.13 | I5: =H5*(1-$E$8) -> 0.117 | J5: =I5*(1-$E$8) -> 0.1053 | K5: =J5*(1-$E$8) -> 0.09477 | L5: =K5*(1-$E$8) -> 0.085293 | M5: =L5*(1-$E$8) -> 0.0767637 | N5: =M5*(1-$E$8) -> 0.06908733 | O5: =N5*(1-$E$8) -> 0.062178597 | P5: =O5*(1-$E$8) -> 0.055960737 | Q5: =P5*(1-$E$8) -> 0.050364664
D6: Bull Case | E6: =MAX(Model!H7:L7) -> 0.22248176 | H6: 0.22248176 | I6: =H6*(1-$E$8) -> 0.20023359 | J6: =I6*(1-$E$8) -> 0.18021023 | K6: =J6*(1-$E$8) -> 0.1621892 | L6: =K6*(1-$E$8) -> 0.14597028 | M6: =L6*(1-$E$8) -> 0.13137326 | N6: =M6*(1-$E$8) -> 0.11823593 | O6: =N6*(1-$E$8) -> 0.10641234 | P6: =O6*(1-$E$8) -> 0.095771103 | Q6: =P6*(1-$E$8) -> 0.086193993
D7: Bear Case | E7: 0.075 | H7: 0.075 | I7: =H7*(1-$E$8) -> 0.0675 | J7: =I7*(1-$E$8) -> 0.06075 | K7: =J7*(1-$E$8) -> 0.054675 | L7: =K7*(1-$E$8) -> 0.0492075 | M7: =L7*(1-$E$8) -> 0.04428675 | N7: =M7*(1-$E$8) -> 0.039858075 | O7: =N7 -> 0.039858075 | P7: =O7 -> 0.039858075 | Q7: =P7 -> 0.039858075
D8: Annual Growth Tapering | E8: 0.1
D9: 5 years CAGR | E9: 0.1677
D10: Average Revenue growth | E10: =AVERAGE(Model!I7:L7) -> 0.14109514
D12: Assumptions
D13: {=D5:D7} -> Base Case | E13: I use 13% as a slightly conservative starting point against Star Cement's ~14% FY22–FY26 revenue CAGR, while factoring in the additional growth expected from the announced capacity expansion.
D14: Bull Case | E14: I assume 22.2% near-term growth to reflect a strong capacity ramp-up, supported by Star Cement's planned increase from 9.7 MTPA to 16.7 MTPA by FY29, along with stronger demand and realisation
D15: Bear Case | E15: I use 7.5% as the downside starting point because it is broadly aligned with the 7–8% FY27 industry cement-volume growth outlook, assuming Star gains little additional market share from the expansion.
D19: Annual Report 2024-25 Corporate Overview | O19: Star Cemenst Investors Presentation -Quarter 4 FY 26
D41: IBEF Cement Industry Report

Sheet Comp Data
B2: S.No. | C2: Name | D2: CMP Rs. | E2: P/E | F2: Mar Cap Rs.Cr. | G2: EV / EBITDA | H2: No. Eq. Shares Cr. | I2: No. Eq. Shares PY Cr. | J2: Debt Rs.Cr. | K2: EV Rs.Cr. | L2: CMP / FCF | M2: EBIDT Ann Rs.Cr. | N2: PAT 12M Rs.Cr. | O2: Sales Rs.Cr. | P2: NP Ann Rs.Cr. | Q2: ROE % | R2: ROCE % | S2: EBIT 12M Rs.Cr. | T2: Cash Rs.Cr. | U2: Tax Rate | V2: Levered Beta
B3: 1 | C3: UltraTech Cem. | D3: 11943.75 | E3: 40.86 | F3: 351957.43 | G3: 20.63 | H3: 29.47 | I3: 29.47 | J3: 23755.09 | K3: 374328.17 | L3: 110.67 | M3: 17457.54 | N3: 8624.55 | O3: 91884.28 | P3: 8188.35 | Q3: 11.1 | R3: 12.66 | S3: 13404.58 | T3: 11967.25 | U3: 0.16051272 | V3: 1.152
B4: 2 | C4: Grasim Inds | D4: 3130.3 | E4: 42.57 | F4: 213025.83 | G4: 11.61 | H4: 68.05 | I4: 68.05 | J4: 227853.06 | K4: 434690.63 | L4: -6.6 | M4: 37454.09 | N4: 5004.75 | O4: 175430.74 | P4: 10300.29 | Q4: 4.98 | R4: 8.01 | S4: 29728.15 | T4: 3125.5 | U4: 0.2835 | V4: 1.164
B5: 3 | C5: Ambuja Cements | D5: 440.1 | E5: 23.22 | F5: 109356.77 | G5: 15.76 | H5: 248.48 | I5: 246.31 | J5: 865.93 | K5: 109264.1 | L5: -63.06 | M5: 7428.67 | N5: 4708.12 | O5: 39867.14 | P5: 5637.08 | Q5: 8.85 | R5: 5.61 | S5: 3251.64 | T5: 440.05 | U5: 0.20360569 | V5: 1.164
B6: 4 | C6: Shree Cement | D6: 26844.3 | E6: 59.42 | F6: 96856.23 | G6: 18.87 | H6: 3.61 | I6: 3.61 | J6: 1868.14 | K6: 98382.58 | L6: 97.1 | M6: 5249.56 | N6: 1630.09 | O6: 21895.72 | P6: 1748.66 | Q6: 7.51 | R6: 10.27 | S6: 2388.66 | T6: 26884.65 | U6: 0.20967554 | V6: 1.007
B7: 5 | C7: J K Cements | D7: 5512.35 | E7: 43.6 | F7: 42592.97 | G7: 19.23 | H7: 7.73 | I7: 7.73 | J7: 6182.99 | K7: 48306.85 | L7: 194.51 | M7: 2567.53 | N7: 976.47 | O7: 14401.49 | P7: 987.99 | Q7: 15.61 | R7: 15.1 | S7: 1838.48 | T7: 5494.8 | U7: 0.48041414 | V7: 1.214
B8: 6 | C8: Dalmia BharatLtd | D8: 1811 | E8: 30.91 | F8: 33968.2 | G8: 12.41 | H8: 18.76 | I8: 18.76 | J8: 7406 | K8: 41150.2 | L8: -283.12 | M8: 3199 | N8: 1098.42 | O8: 15058 | P8: 1157 | Q8: 6.11 | R8: 7.59 | S8: 1929 | T8: 1810 | U8: 0.20392928 | V8: 1.244
B9: 7 | C9: ACC | D9: 1388 | E9: 13.75 | F9: 26064.88 | G9: 8.58 | H9: 18.78 | I9: 18.78 | J9: 428.61 | K9: 25935.76 | L9: -79.13 | M9: 3366.76 | N9: 1899.74 | O9: 25441.73 | P9: 2137.23 | Q9: 10.86 | R9: 11.25 | S9: 1898.25 | T9: 1388.2 | U9: 0.29358228 | V9: 1.12
B10: 8 | C10: The Ramco Cement | D10: 944.15 | E10: 753.09 | F10: 22309.58 | G10: 17.56 | H10: 23.63 | I10: 23.63 | J10: 3871.1 | K10: 25953.39 | L10: 40.39 | M10: 1478.02 | N10: 698.65 | O10: 9028.76 | P10: 698.79 | Q10: 0.38 | R10: 6.13 | S10: 737.86 | T10: 945.95 | U10: 0.32532742 | V10: 0.97
B11: 9 | C11: JSW Cement | D11: 131.75 | E11: 27.53 | F11: 17962.33 | G11: 15.38 | H11: 136.34 | I11: 101.89 | J11: 4464.39 | K11: 21926.98 | L11: -74.31 | M11: 1425.22 | N11: 653.23 | O11: 6501.28 | P11: -798.78 | Q11: 14.67 | R11: 11.07 | S11: 1102.98 | T11: 131.7 | U11: 0.76502916 | V11: 1.03
B12: 10 | C12: Nuvoco Vistas | D12: 347.25 | E12: 29.92 | F12: 12402.2 | G12: 8.97 | H12: 35.72 | I12: 35.72 | J12: 4916.1 | K12: 17222.04 | L12: 13.45 | M12: 1880.92 | N12: 414.99 | O12: 11594.3 | P12: 359.77 | Q12: 4.05 | R12: 7.07 | S12: 1024.51 | T12: 348 | U12: 0.2319574 | V12: 0.879
B13: 11 | C13: India Cements | D13: 396 | E13: 90.9 | F13: 12271.91 | G13: 24.53 | H13: 30.99 | I13: 30.99 | J13: 1304.8 | K13: 13516.11 | L13: 215.22 | M13: 440.67 | N13: 135 | O13: 4479.37 | P13: -67.25 | Q13: 0.37 | R13: 1.24 | S13: 254.01 | T13: 391.45 | U13: 0.44888889 | V13: 1.394
B14: 12 | C14: Star Cement | D14: 203.35 | E14: 20.45 | F14: 8218.98 | G14: 9.11 | H14: 40.42 | I14: 40.42 | J14: 603.33 | K14: 8697.64 | L14: -45.05 | M14: 955.21 | N14: 401.72 | O14: 3776.49 | P14: 390.45 | Q14: 13.24 | R14: 16.68 | S14: 589.92 | T14: 203.4 | U14: 0.31034054 | V14: 0.75
B15: 13 | C15: JK Lakshmi Cem. | D15: 570.1 | E15: 17.81 | F15: 7077.46 | G15: 8.46 | H15: 12.41 | I15: 11.77 | J15: 2585.78 | K15: 9149.26 | L15: 49.16 | M15: 1081.82 | N15: 397.54 | O15: 6762.63 | P15: 412.61 | Q15: 10.69 | R15: 12 | S15: 758.04 | T15: 571.4 | U15: 0.11470544 | V15: 1.119

Sheet Comps
A1: Star Cements
A2: Comps Valuation
H5: Market Data | O5: Financial Data | S5: Valuation Metrics
H6: Price | I6: Shares | J6: Market Cap | K6: Debt | L6: Cash | M6: EV | O6: Sale | P6: EBITDA | Q6: Earnings | S6: EV/Sales | T6: EV/EBITDA | U6: P/E
D7: Company Name | H7: ₹/share | I7: in Cr | J7: ₹ Cr | K7: ₹ Cr | L7: ₹ Cr | M7: ₹ Cr | O7: ₹ Cr | P7: ₹ Cr | Q7: ₹ Cr | S7: x | T7: x | U7: x
D8: ='Comp Data'!C3 -> UltraTech Cem. | H8: ='Comp Data'!D3 -> 11943.75 | I8: ='Comp Data'!H3 -> 29.47 | J8: =H8*I8 -> 351982.31 | K8: ='Comp Data'!J3 -> 23755.09 | L8: ='Comp Data'!T3 -> 11967.25 | M8: ='Comp Data'!K3 -> 374328.17 | O8: ='Comp Data'!O3 -> 91884.28 | P8: ='Comp Data'!M3 -> 17457.54 | Q8: ='Comp Data'!N3 -> 8624.55 | S8: =M8/O8 -> 4.0739087 | T8: =M8/P8 -> 21.442206 | U8: =J8/Q8 -> 40.811673
D9: ='Comp Data'!C4 -> Grasim Inds | H9: ='Comp Data'!D4 -> 3130.3 | I9: ='Comp Data'!H4 -> 68.05 | J9: =H9*I9 -> 213016.92 | K9: ='Comp Data'!J4 -> 227853.06 | L9: ='Comp Data'!T4 -> 3125.5 | M9: ='Comp Data'!K4 -> 434690.63 | O9: ='Comp Data'!O4 -> 175430.74 | P9: ='Comp Data'!M4 -> 37454.09 | Q9: ='Comp Data'!N4 -> 5004.75 | S9: =M9/O9 -> 2.4778476 | T9: =M9/P9 -> 11.605959 | U9: =J9/Q9 -> 42.562948
D10: ='Comp Data'!C5 -> Ambuja Cements | H10: ='Comp Data'!D5 -> 440.1 | I10: ='Comp Data'!H5 -> 248.48 | J10: =H10*I10 -> 109356.05 | K10: ='Comp Data'!J5 -> 865.93 | L10: ='Comp Data'!T5 -> 440.05 | M10: ='Comp Data'!K5 -> 109264.1 | O10: ='Comp Data'!O5 -> 39867.14 | P10: ='Comp Data'!M5 -> 7428.67 | Q10: ='Comp Data'!N5 -> 4708.12 | S10: =M10/O10 -> 2.7407058 | T10: =M10/P10 -> 14.708434 | U10: =J10/Q10 -> 23.227116
D11: ='Comp Data'!C6 -> Shree Cement | H11: ='Comp Data'!D6 -> 26844.3 | I11: ='Comp Data'!H6 -> 3.61 | J11: =H11*I11 -> 96907.923 | K11: ='Comp Data'!J6 -> 1868.14 | L11: ='Comp Data'!T6 -> 26884.65 | M11: ='Comp Data'!K6 -> 98382.58 | O11: ='Comp Data'!O6 -> 21895.72 | P11: ='Comp Data'!M6 -> 5249.56 | Q11: ='Comp Data'!N6 -> 1630.09 | S11: =M11/O11 -> 4.4932334 | T11: =M11/P11 -> 18.74111 | U11: =J11/Q11 -> 59.449431
D12: ='Comp Data'!C7 -> J K Cements | H12: ='Comp Data'!D7 -> 5512.35 | I12: ='Comp Data'!H7 -> 7.73 | J12: =H12*I12 -> 42610.466 | K12: ='Comp Data'!J7 -> 6182.99 | L12: ='Comp Data'!T7 -> 5494.8 | M12: ='Comp Data'!K7 -> 48306.85 | O12: ='Comp Data'!O7 -> 14401.49 | P12: ='Comp Data'!M7 -> 2567.53 | Q12: ='Comp Data'!N7 -> 976.47 | S12: =M12/O12 -> 3.3542953 | T12: =M12/P12 -> 18.814522 | U12: =J12/Q12 -> 43.63725
D13: ='Comp Data'!C8 -> Dalmia BharatLtd | H13: ='Comp Data'!D8 -> 1811 | I13: ='Comp Data'!H8 -> 18.76 | J13: =H13*I13 -> 33974.36 | K13: ='Comp Data'!J8 -> 7406 | L13: ='Comp Data'!T8 -> 1810 | M13: ='Comp Data'!K8 -> 41150.2 | O13: ='Comp Data'!O8 -> 15058 | P13: ='Comp Data'!M8 -> 3199 | Q13: ='Comp Data'!N8 -> 1098.42 | S13: =M13/O13 -> 2.7327799 | T13: =M13/P13 -> 12.863457 | U13: =J13/Q13 -> 30.930209
D14: ='Comp Data'!C9 -> ACC | H14: ='Comp Data'!D9 -> 1388 | I14: ='Comp Data'!H9 -> 18.78 | J14: =H14*I14 -> 26066.64 | K14: ='Comp Data'!J9 -> 428.61 | L14: ='Comp Data'!T9 -> 1388.2 | M14: ='Comp Data'!K9 -> 25935.76 | O14: ='Comp Data'!O9 -> 25441.73 | P14: ='Comp Data'!M9 -> 3366.76 | Q14: ='Comp Data'!N9 -> 1899.74 | S14: =M14/O14 -> 1.0194181 | T14: =M14/P14 -> 7.7034775 | U14: =J14/Q14 -> 13.721162
D15: ='Comp Data'!C10 -> The Ramco Cement | H15: ='Comp Data'!D10 -> 944.15 | I15: ='Comp Data'!H10 -> 23.63 | J15: =H15*I15 -> 22310.264 | K15: ='Comp Data'!J10 -> 3871.1 | L15: ='Comp Data'!T10 -> 945.95 | M15: ='Comp Data'!K10 -> 25953.39 | O15: ='Comp Data'!O10 -> 9028.76 | P15: ='Comp Data'!M10 -> 1478.02 | Q15: ='Comp Data'!N10 -> 698.65 | S15: =M15/O15 -> 2.8745243 | T15: =M15/P15 -> 17.559566 | U15: =J15/Q15 -> 31.933392
D16: ='Comp Data'!C11 -> JSW Cement | H16: ='Comp Data'!D11 -> 131.75 | I16: ='Comp Data'!H11 -> 136.34 | J16: =H16*I16 -> 17962.795 | K16: ='Comp Data'!J11 -> 4464.39 | L16: ='Comp Data'!T11 -> 131.7 | M16: ='Comp Data'!K11 -> 21926.98 | O16: ='Comp Data'!O11 -> 6501.28 | P16: ='Comp Data'!M11 -> 1425.22 | Q16: ='Comp Data'!N11 -> 653.23 | S16: =M16/O16 -> 3.3727174 | T16: =M16/P16 -> 15.384979 | U16: =J16/Q16 -> 27.498423
D17: ='Comp Data'!C12 -> Nuvoco Vistas | H17: ='Comp Data'!D12 -> 347.25 | I17: ='Comp Data'!H12 -> 35.72 | J17: =H17*I17 -> 12403.77 | K17: ='Comp Data'!J12 -> 4916.1 | L17: ='Comp Data'!T12 -> 348 | M17: ='Comp Data'!K12 -> 17222.04 | O17: ='Comp Data'!O12 -> 11594.3 | P17: ='Comp Data'!M12 -> 1880.92 | Q17: ='Comp Data'!N12 -> 414.99 | S17: =M17/O17 -> 1.4853885 | T17: =M17/P17 -> 9.1561789 | U17: =J17/Q17 -> 29.889323
D18: ='Comp Data'!C13 -> India Cements | H18: ='Comp Data'!D13 -> 396 | I18: ='Comp Data'!H13 -> 30.99 | J18: =H18*I18 -> 12272.04 | K18: ='Comp Data'!J13 -> 1304.8 | L18: ='Comp Data'!T13 -> 391.45 | M18: ='Comp Data'!K13 -> 13516.11 | O18: ='Comp Data'!O13 -> 4479.37 | P18: ='Comp Data'!M13 -> 440.67 | Q18: ='Comp Data'!N13 -> 135 | S18: =M18/O18 -> 3.0174132 | T18: =M18/P18 -> 30.671727 | U18: =J18/Q18 -> 90.904
D19: ='Comp Data'!C14 -> Star Cement | H19: ='Market Data'!B265 -> 198.94 | I19: ='Comp Data'!H14 -> 40.42 | J19: =H19*I19 -> 8041.1548 | K19: ='Comp Data'!J14 -> 603.33 | L19: ='Comp Data'!T14 -> 203.4 | M19: ='Comp Data'!K14 -> 8697.64 | O19: ='Comp Data'!O14 -> 3776.49 | P19: ='Comp Data'!M14 -> 955.21 | Q19: ='Comp Data'!N14 -> 401.72 | S19: =M19/O19 -> 2.3031016 | T19: =M19/P19 -> 9.1054742 | U19: =J19/Q19 -> 20.016815
D20: ='Comp Data'!C15 -> JK Lakshmi Cem. | H20: ='Comp Data'!D15 -> 570.1 | I20: ='Comp Data'!H15 -> 12.41 | J20: =H20*I20 -> 7074.941 | K20: ='Comp Data'!J15 -> 2585.78 | L20: ='Comp Data'!T15 -> 571.4 | M20: ='Comp Data'!K15 -> 9149.26 | O20: ='Comp Data'!O15 -> 6762.63 | P20: ='Comp Data'!M15 -> 1081.82 | Q20: ='Comp Data'!N15 -> 397.54 | S20: =M20/O20 -> 1.3529145 | T20: =M20/P20 -> 8.4572849 | U20: =J20/Q20 -> 17.796803
D22: Average | S22: =AVERAGE(S8:S15) -> 2.9708391 | T22: =AVERAGE(T8:T15) -> 15.429841 | U22: =AVERAGE(U8:U15) -> 35.784148
D23: Median | S23: =MEDIAN(S8:S15) -> 2.807615 | T23: =MEDIAN(T8:T15) -> 16.134 | U23: =MEDIAN(U8:U15) -> 36.372533
D25: =D19 -> Star Cement | H25: =H19 -> 198.94 | I25: =I19 -> 40.42 | J25: =J19 -> 8041.1548 | K25: =K19 -> 603.33 | L25: =L19 -> 203.4 | M25: =M19 -> 8697.64 | O25: =O19 -> 3776.49 | P25: =P19 -> 955.21 | Q25: =Q19 -> 401.72 | S25: =S19 -> 2.3031016 | T25: =T19 -> 9.1054742 | U25: =U19 -> 20.016815
D27: Metric | E27: Comps | H27: EV | I27: Net Debt | J27: Equity Value | K27: Shares | L27: Share Price
D28: {=TRANSPOSE(S6:U6)} -> EV/Sales | E28: {=TRANSPOSE(S22:U22)} -> 2.9708391 | H28: =E28*O25 -> 11219.344 | I28: =K25-L25 -> 399.93 | J28: =H28-I28 -> 10819.414 | K28: =I25 -> 40.42 | L28: =J28/K28 -> 267.67477
D29: EV/EBITDA | E29: 15.429841 | H29: =E29*P25 -> 14738.739 | I29: =I28 -> 399.93 | J29: =H29-I29 -> 14338.809 | K29: =K28 -> 40.42 | L29: =J29/K29 -> 354.74539
D30: P/E | E30: 35.784148 | H30: =SUM(I30:J30) -> 14775.138 | I30: =I29 -> 399.93 | J30: =E30*Q25 -> 14375.208 | K30: =K29 -> 40.42 | L30: =J30/K30 -> 355.64591

Sheet WACC
A1: Star Cements
A2: Weigthed Average Cost of Capital
A5: Comparable Companies Beta
H6: Equity | I6: Total | J6: Debt/ | K6: Debt/ | L6: Tax | M6: Levered | N6: Unlevered
D7: Name | H7: Value | I7: Debt | J7: Equity | K7: Capital | L7: Rate% | M7: Beta | N7: Beta
D8: ='Comp Data'!C3 -> UltraTech Cem. | H8: =Comps!J8 -> 351982.31 | I8: =Comps!K8 -> 23755.09 | J8: =I8/H8 -> 0.067489442 | K8: =I8/(I8+H8) -> 0.063222585 | L8: ='Comp Data'!U3 -> 0.16051272 | M8: ='Comp Data'!V3 -> 1.152 | N8: =M8/(J8*(1-L8)+1) -> 1.0902313
D9: ='Comp Data'!C4 -> Grasim Inds | H9: =Comps!J9 -> 213016.92 | I9: =Comps!K9 -> 227853.06 | J9: =I9/H9 -> 1.0696477 | K9: =I9/(I9+H9) -> 0.51682599 | L9: ='Comp Data'!U4 -> 0.2835 | M9: ='Comp Data'!V4 -> 1.164 | N9: =M9/(J9*(1-L9)+1) -> 0.65896642
D10: ='Comp Data'!C5 -> Ambuja Cements | H10: =Comps!J10 -> 109356.05 | I10: =Comps!K10 -> 865.93 | J10: =I10/H10 -> 0.0079184464 | K10: =I10/(I10+H10) -> 0.0078562372 | L10: ='Comp Data'!U5 -> 0.20360569 | M10: ='Comp Data'!V5 -> 1.164 | N10: =M10/(J10*(1-L10)+1) -> 1.1567056
D11: ='Comp Data'!C6 -> Shree Cement | H11: =Comps!J11 -> 96907.923 | I11: =Comps!K11 -> 1868.14 | J11: =I11/H11 -> 0.019277474 | K11: =I11/(I11+H11) -> 0.018912882 | L11: ='Comp Data'!U6 -> 0.20967554 | M11: ='Comp Data'!V6 -> 1.007 | N11: =M11/(J11*(1-L11)+1) -> 0.99188813
D12: ='Comp Data'!C7 -> J K Cements | H12: =Comps!J12 -> 42610.466 | I12: =Comps!K12 -> 6182.99 | J12: =I12/H12 -> 0.14510496 | K12: =I12/(I12+H12) -> 0.12671761 | L12: ='Comp Data'!U7 -> 0.48041414 | M12: ='Comp Data'!V7 -> 1.214 | N12: =M12/(J12*(1-L12)+1) -> 1.1288881
D13: ='Comp Data'!C8 -> Dalmia BharatLtd | H13: =Comps!J13 -> 33974.36 | I13: =Comps!K13 -> 7406 | J13: =I13/H13 -> 0.21798792 | K13: =I13/(I13+H13) -> 0.17897379 | L13: ='Comp Data'!U8 -> 0.20392928 | M13: ='Comp Data'!V8 -> 1.244 | N13: =M13/(J13*(1-L13)+1) -> 1.0600462
D14: ='Comp Data'!C9 -> ACC | H14: =Comps!J14 -> 26066.64 | I14: =Comps!K14 -> 428.61 | J14: =I14/H14 -> 0.016442856 | K14: =I14/(I14+H14) -> 0.016176862 | L14: ='Comp Data'!U9 -> 0.29358228 | M14: ='Comp Data'!V9 -> 1.12 | N14: =M14/(J14*(1-L14)+1) -> 1.10714
D15: ='Comp Data'!C10 -> The Ramco Cement | H15: =Comps!J15 -> 22310.264 | I15: =Comps!K15 -> 3871.1 | J15: =I15/H15 -> 0.17351206 | K15: =I15/(I15+H15) -> 0.14785708 | L15: ='Comp Data'!U10 -> 0.32532742 | M15: ='Comp Data'!V10 -> 0.97 | N15: =M15/(J15*(1-L15)+1) -> 0.86834787
D16: ='Comp Data'!C11 -> JSW Cement | H16: =Comps!J16 -> 17962.795 | I16: =Comps!K16 -> 4464.39 | J16: =I16/H16 -> 0.24853538 | K16: =I16/(I16+H16) -> 0.19906154 | L16: ='Comp Data'!U11 -> 0.76502916 | M16: ='Comp Data'!V11 -> 1.03 | N16: =M16/(J16*(1-L16)+1) -> 0.97316836
D17: ='Comp Data'!C12 -> Nuvoco Vistas | H17: =Comps!J17 -> 12403.77 | I17: =Comps!K17 -> 4916.1 | J17: =I17/H17 -> 0.39633918 | K17: =I17/(I17+H17) -> 0.28384162 | L17: ='Comp Data'!U12 -> 0.2319574 | M17: ='Comp Data'!V12 -> 0.879 | N17: =M17/(J17*(1-L17)+1) -> 0.67387027
D18: ='Comp Data'!C13 -> India Cements | H18: =Comps!J18 -> 12272.04 | I18: =Comps!K18 -> 1304.8 | J18: =I18/H18 -> 0.10632299 | K18: =I18/(I18+H18) -> 0.096104837 | L18: ='Comp Data'!U13 -> 0.44888889 | M18: ='Comp Data'!V13 -> 1.394 | N18: =M18/(J18*(1-L18)+1) -> 1.3168388
D19: ='Comp Data'!C14 -> Star Cement | H19: =Comps!J19 -> 8041.1548 | I19: =Comps!K19 -> 603.33 | J19: =I19/H19 -> 0.075030268 | K19: =I19/(I19+H19) -> 0.069793633 | L19: ='Comp Data'!U14 -> 0.31034054 | M19: ='Comp Data'!V14 -> 0.75 | N19: =M19/(J19*(1-L19)+1) -> 0.71310038
D20: ='Comp Data'!C15 -> JK Lakshmi Cem. | H20: =Comps!J20 -> 7074.941 | I20: =Comps!K20 -> 2585.78 | J20: =I20/H20 -> 0.36548432 | K20: =I20/(I20+H20) -> 0.26765911 | L20: ='Comp Data'!U15 -> 0.11470544 | M20: ='Comp Data'!V15 -> 1.119 | N20: =M20/(J20*(1-L20)+1) -> 0.84544631
D22: Average | H22: =AVERAGE(H8:H20) -> 73383.048 | I22: =AVERAGE(I8:I20) -> 22008.102 | J22: =AVERAGE(J8:J20) -> 0.22377639 | K22: =AVERAGE(K8:K20) -> 0.15330798 | L22: =AVERAGE(L8:L20) -> 0.31011296 | M22: =AVERAGE(M8:M20) -> 1.0928462 | N22: =AVERAGE(N8:N20) -> 0.96804905
D23: Median | H23: =MEDIAN(H9:H21) -> 24188.452 | I23: =MEDIAN(I9:I21) -> 3228.44 | J23: =MEDIAN(J8:J20) -> 0.14510496 | K23: =MEDIAN(K8:K20) -> 0.12671761 | L23: =MEDIAN(L8:L20) -> 0.2835 | M23: =MEDIAN(M8:M20) -> 1.12 | N23: =MEDIAN(N8:N20) -> 0.99188813
D25: =D19 -> Star Cement | H25: =H19 -> 8041.1548 | I25: =I19 -> 603.33 | J25: =J19 -> 0.075030268 | K25: =K19 -> 0.069793633 | L25: =L19 -> 0.31034054 | M25: =M19 -> 0.75 | N25: =N19 -> 0.71310038
A27: WACC Calculation
C29: Target Capital Structure
D31: Proportion of Debt | H31: =K23 -> 0.12671761
D32: Proportion Of Equity | H32: =1-H31 -> 0.87328239
C34: Current Capital Structure
D35: Market Cap | H35: =H25 -> 8041.1548
D36: Total Debt | H36: =I25 -> 603.33
D37: Debt/ Equity | H37: =J25 -> 0.075030268
C39: Cost of Debt
D40: Pre Tax Cost of Debt | H40: =Model!M12 -> 0.057931467
D41: Tax Rate | H41: =Model!M13 -> 0.25560461
D42: After Tax Cost of Debt | H42: =H40*(1-H41) -> 0.043123917
C44: Cost of Equity
D45: Risk Free Rate | H45: 0.0703
D46: Equity Market Return | H46: ='Market Data'!H9 -> 0.11561682
D47: Equity Risk Premium | H47: =H46-H45 -> 0.045316819
D48: Levered Equity Beta | H48: =N22*(1+H37*(1-H41)) -> 1.0221167
D49: Cost of Equity | H49: =H45+H47*H48 -> 0.11661908
D51: WACC | H51: =(H49*H32)+(H42*H31) -> 0.10730595

Sheet Beta
A1: Star Cements
A2: Company Beta(Regression)
A3: Date | B3: Britannia Price | C3: Nifty Price | D3: Britannia Return | E3: Nifty Return
A4: 44417 | B4: 115.11896 | C4: 16529.1 | D4: -0.018763694 | E4: 0.033894726
A5: =A4+7 -> 44424 | B5: 114.72216 | C5: 16450.5 | D5: =B5/B4-1 -> -0.0034468448 | E5: =C5/C4-1 -> -0.0047552263
A6: =A5+7 -> 44431 | B6: 105.89356 | C6: 16705.199 | D6: =B6/B5-1 -> -0.076956344 | E6: =C6/C5-1 -> 0.015482765
A7: =A6+7 -> 44438 | B7: 106.33995 | C7: 17323.6 | D7: =B7/B6-1 -> 0.0042154427 | E7: =C7/C6-1 -> 0.037018439
A8: =A7+7 -> 44445 | B8: 106.43916 | C8: 17369.25 | D8: =B8/B7-1 -> 0.00093290449 | E8: =C8/C7-1 -> 0.0026351562
A9: =A8+7 -> 44452 | B9: 107.77832 | C9: 17585.15 | D9: =B9/B8-1 -> 0.012581505 | E9: =C9/C8-1 -> 0.012430035
A10: =A9+7 -> 44459 | B10: 106.98473 | C10: 17853.199 | D10: =B10/B9-1 -> -0.0073631388 | E10: =C10/C9-1 -> 0.015242908
A11: =A10+7 -> 44466 | B11: 106.38955 | C11: 17532.051 | D11: =B11/B10-1 -> -0.0055632641 | E11: =C11/C10-1 -> -0.017988285 | H11: Beta | I11: =SLOPE(D4:D272,E4:E272) -> 0.72968523
A12: =A11+7 -> 44473 | B12: 105.64557 | C12: 17895.199 | D12: =B12/B11-1 -> -0.0069929839 | E12: =C12/C11-1 -> 0.020713403 | H12: Rsquare | I12: =RSQ(D4:D272,E4:E272) -> 0.10279599
A13: =A12+7 -> 44480 | B13: 103.06643 | C13: 18338.551 | D13: =B13/B12-1 -> -0.024413137 | E13: =C13/C12-1 -> 0.024774888
A14: =A13+7 -> 44487 | B14: 99.842499 | C14: 18114.9 | D14: =B14/B13-1 -> -0.031280121 | E14: =C14/C13-1 -> -0.012195641
A15: =A14+7 -> 44494 | B15: 98.999321 | C15: 17671.65 | D15: =B15/B14-1 -> -0.0084450791 | E15: =C15/C14-1 -> -0.024468807
A16: =A15+7 -> 44501 | B16: 99.7929 | C16: 17916.801 | D16: =B16/B15-1 -> 0.0080160055 | E16: =C16/C15-1 -> 0.013872524
A17: =A16+7 -> 44508 | B17: 101.33047 | C17: 18102.75 | D17: =B17/B16-1 -> 0.01540758 | E17: =C17/C16-1 -> 0.010378483
A18: =A17+7 -> 44515 | B18: 96.717773 | C18: 17764.801 | D18: =B18/B17-1 -> -0.045521292 | E18: =C18/C17-1 -> -0.018668391
A19: =A18+7 -> 44522 | B19: 94.337029 | C19: 17026.449 | D19: =B19/B18-1 -> -0.024615382 | E19: =C19/C18-1 -> -0.041562614
A20: =A19+7 -> 44529 | B20: 96.56897 | C20: 17196.699 | D20: =B20/B19-1 -> 0.023659228 | E20: =C20/C19-1 -> 0.0099991488
A21: =A20+7 -> 44536 | B21: 95.924187 | C21: 17511.301 | D21: =B21/B20-1 -> -0.0066769173 | E21: =C21/C20-1 -> 0.018294299
A22: =A21+7 -> 44543 | B22: 93.741844 | C22: 16985.199 | D22: =B22/B21-1 -> -0.022750701 | E22: =C22/C21-1 -> -0.030043546
A23: =A22+7 -> 44550 | B23: 93.841042 | C23: 17003.75 | D23: =B23/B22-1 -> 0.0010581975 | E23: =C23/C22-1 -> 0.0010921733
A24: =A23+7 -> 44557 | B24: 94.535431 | C24: 17354.051 | D24: =B24/B23-1 -> 0.0073996338 | E24: =C24/C23-1 -> 0.020601384
... A265: =A264+7 -> 46244 | B265: 198.94 | C265: 24583.8 | D265: =B265/B264-1 -> -0.023463583 | E265: =C265/C264-1 -> -0.0012634782

Sheet Market Data
A1: Britannia Industries Limited
A2: Market Return
A3: Date | B3: Britannia Price | C3: Nifty Price | D3: Britannia Return | E3: Nifty Return
A4: =Beta!A4 -> 44417 | B4: =Beta!B4 -> 115.11896 | C4: =Beta!C4 -> 16529.1 | D4: -0.018763694 | E4: 0.033894726
A5: =Beta!A5 -> 44424 | B5: =Beta!B5 -> 114.72216 | C5: =Beta!C5 -> 16450.5 | D5: -0.003580021 | E5: 0.017156207
A6: =Beta!A6 -> 44431 | B6: =Beta!B6 -> 105.89356 | C6: =Beta!C6 -> 16705.199 | D6: 0.02301934 | E6: 0.015198557
A7: =Beta!A7 -> 44438 | B7: =Beta!B7 -> 106.33995 | C7: =Beta!C7 -> 17323.6 | D7: 0.019660032 | E7: 0.0082385163 | G7: No. of Years | H7: 5
A8: =Beta!A8 -> 44445 | B8: =Beta!B8 -> 106.43916 | C8: =Beta!C8 -> 17369.25 | D8: 0.01722934 | E8: -0.0073420744 | G8: Index | H8: Nifty 50
A9: =Beta!A9 -> 44452 | B9: =Beta!B9 -> 107.77832 | C9: =Beta!C9 -> 17585.15 | D9: 0.014050093 | E9: 0.011285854 | G9: Market Return | H9: =_xlfn.RRI(H7,B4,B265) -> 0.11561682
A10: =Beta!A10 -> 44459 | B10: =Beta!B10 -> 106.98473 | C10: =Beta!C10 -> 17853.199 | D10: -0.033991427 | E10: -0.0087103637 | G10: Levered Beta | H10: =SLOPE(D4:D265,E4:E265) -> 0.52481397
A11: =Beta!A11 -> 44466 | B11: =Beta!B11 -> 106.38955 | C11: =Beta!C11 -> 17532.051 | D11: -0.019561043 | E11: -0.0020608051 | G11: 52 Weeks Hi | H11: =MAX(B217:B265) -> 272.20319
A12: =Beta!A12 -> 44473 | B12: =Beta!B12 -> 105.64557 | C12: =Beta!C12 -> 17895.199 | D12: -0.010054864 | E12: 0.014888691 | G12: 52 Weeks lo | H12: =MIN(B217:B265) -> 198.94
A13: =Beta!A13 -> 44480 | B13: =Beta!B13 -> 103.06643 | C13: =Beta!C13 -> 18338.551 | D13: -0.00034868229 | E13: -0.004229661
A14: =Beta!A14 -> 44487 | B14: =Beta!B14 -> 99.842499 | C14: =Beta!C14 -> 18114.9 | D14: -0.0047677907 | E14: -0.0058652692
A15: =Beta!A15 -> 44494 | B15: =Beta!B15 -> 98.999321 | C15: =Beta!C15 -> 17671.65 | D15: 0.052754651 | E15: 0.030143303
A16: =Beta!A16 -> 44501 | B16: =Beta!B16 -> 99.7929 | C16: =Beta!C16 -> 17916.801 | D16: -0.0067841297 | E16: 0.017914511
A17: =Beta!A17 -> 44508 | B17: =Beta!B17 -> 101.33047 | C17: =Beta!C17 -> 18102.75 | D17: 0.088390869 | E17: -0.0047552263
A18: =Beta!A18 -> 44515 | B18: =Beta!B18 -> 96.717773 | C18: =Beta!C18 -> 17764.801 | D18: 0.011704529 | E18: 0.015482765
A19: =Beta!A19 -> 44522 | B19: =Beta!B19 -> 94.337029 | C19: =Beta!C19 -> 17026.449 | D19: 0.046339747 | E19: 0.037018439
A20: =Beta!A20 -> 44529 | B20: =Beta!B20 -> 96.56897 | C20: =Beta!C20 -> 17196.699 | D20: -0.012948051 | E20: 0.0026351562
A21: =Beta!A21 -> 44536 | B21: =Beta!B21 -> 95.924187 | C21: =Beta!C21 -> 17511.301 | D21: -0.0046551009 | E21: 0.012430035
A22: =Beta!A22 -> 44543 | B22: =Beta!B22 -> 93.741844 | C22: =Beta!C22 -> 16985.199 | D22: -0.0022089656 | E22: 0.015242908
A23: =Beta!A23 -> 44550 | B23: =Beta!B23 -> 93.841042 | C23: =Beta!C23 -> 17003.75 | D23: -0.030126818 | E23: -0.017988285
A24: =Beta!A24 -> 44557 | B24: =Beta!B24 -> 94.535431 | C24: =Beta!C24 -> 17354.051 | D24: -0.0096401264 | E24: 0.020713403
... A263: =Beta!A263 -> 46230 | B263: =Beta!B263 -> 202.53 | C263: =Beta!C263 -> 24383.6 | D263: -0.035976249 | E263: 0.0074424099
A264: =Beta!A264 -> 46237 | B264: =Beta!B264 -> 203.72 | C264: =Beta!C264 -> 24614.9 | D264: =B264/B263-1 -> 0.0058756848 | E264: =C264/C263-1 -> 0.0094859161
A265: {=Beta!A265:C265} -> 46244 | B265: 198.94 | C265: 24583.8 | D265: =B265/B264-1 -> -0.023463583 | E265: =C265/C264-1 -> -0.0012634782

Sheet Football Field Analysis
A1: Britannia Industries Limited
A2: Valuation Summary : Football Field Analysis
A5: Football Field Data
H7: Comps | I7: DCF | J7: 52-Week hi/lo | K7: Market Consenses
D8: High | H8: =MAX(Comps!L28:L30) -> 355.64591 | I8: 452.14572 | J8: ='Market Data'!H11 -> 272.20319 | K8: 375
D9: High | H9: 355.64591 | I9: 452.14572 | J9: 272.20319 | K9: 375
D10: Low | H10: =MIN(Comps!L28:L30) -> 267.67477 | I10: 207.76966 | J10: 198.94 | K10: 187
D11: Low | H11: 267.67477 | I11: 207.76966 | J11: 198.94 | K11: 187
A13: Valuation Summary
